{
  "scrape_info": {
    "timestamp": "2025-11-11T18:00:06.944941",
    "total_entries": 2,
    "input": "suriyelileri bahane edip şiddetten zevk almak",
    "time_filter": null,
    "filters": [],
    "filter_external_urls": false
  },
  "entries": [
    {
      "title": "suriyelileri bahane edip şiddetten zevk almak",
      "entry_id": "149057668",
      "author": "hgzr",
      "date": "11.02.2023 10:21 ~ 11:19",
      "content": "adam almanya'dan etrafa ayar çekmeye çalışıyor. umarım türkiye'de filansındır turna kardeş yoksa aktroll kadar seviyedesin artık.\n\ntanım: önerme.\n\nedit: adam harbiden olayın ne olduğunu anlamamış. o yönden aktroll seviyesi derken haksızlık etmişim. arkadaş, cidden bazı yerlerde devletin günlerdir olmadığını, kuralsızlığı, yağmayı görmemiş. ama o zaman ülke kalmamış demektir dedi.\n\nkısacası hariçten gazel okuma başlığıdır. başlığı engelleyin geçin.\n\nyağmada her yerde kolluk kuvveti olana kadar, insanların kendi hukukunu koruması esastır. bunun herhangi bir duygu sömürüsüyle değişecek hali yok. kolluk kuvvetinin her yere ya da neredeyse her yere hakimiyeti sonrası sert muamele hem toplumu hem de kolluk kuvvetini çürütür. o ana kadarsa, duyar kasmak hak yemektir.",
      "has_external_url": false
    },
    {
      "title": "suriyelileri bahane edip şiddetten zevk almak",
      "entry_id": "149057915",
      "author": "yanlisbeyin",
      "date": "11.02.2023 10:27 ~ 10:31",
      "content": "herkes çok öfkeli, herkes öfkesini atmaya çalışıyor. ama ilkel reflekslerle hareket etmemiz gereken bir durumda değiliz. bu depremin uzun vadeli sonuçları olacak, belki aylarca, yıllarca toparlanmaya çalışacağız. sağlıksız hamlelerimizin de uzun vadeli sonuçları olacak. çok hızlı galeyana gelen bir halkız maalesef, bu şiddet olayları yarın bir gün size de dönebilir. hukuk bu kritik anlar için var. herkes kendi adaletini sağlamaya kalkarsa, insanların ne kadar iğrenç olabileceğini görüyoruz işte, kimin nasıl cezalandırılacağına karar veren bir mekanizma kalmazsa ortada bunun bize dönüşleri çok ağır olacak çünkü şiddeti normalleştirmiş olacağız, bunu alkışlamış olacağız zaten. cadı avına dönecek mesele. kimse yağmacılığı normalleştirmiyor ama bununla medeni bir şekilde mücadele edilmeli. desteklediğiniz şey çok tehlikeli yerlere varabilir. bu ülkede bir geleceğimiz olacak arkadaşlar, sağlıklı bir halk gibi davranmaya ihtiyacımız var. gerçekten halkın dayanışması çok güçlü, deprem bölgesinde olan olmayan tüm vatandaşlarımız ellerinden geleni yapıyor. bu dayanışma gelecek için de umut verici. korkunç bir dönemden geçiyoruz, bu dayanışmaya uzun vadede ihtiyacımız var. lütfen ama lütfen desteklediğiniz şeyin yarın farklı durumlarda da uygulanabileceğini, kurunun yanında yaşın da yanabileceğini unutmayın. bırakın gerekeni hukuk yapsın. anlık \"çözüm\" getirecek şeyler uzun vadede kolektif bilinçte çok şeyi değiştirir. bunu unutmayın.",
      "has_external_url": false
    }
  ]
}