{
  "scrape_info": {
    "timestamp": "2026-02-07T22:01:58.773590",
    "total_entries": 14,
    "input": "afganistan savaşı",
    "time_filter": null,
    "filters": [],
    "filter_external_urls": false
  },
  "entries": [
    {
      "title": "afganistan savaşı",
      "entry_id": "96772905",
      "author": "jotaro",
      "date": "20.10.2019 15:04 ~ 18.10.2021 14:14",
      "content": "afganistan savaşları nın 2001-2021 arasındaki kısmı.\n\n2001-2014 arası operation enduring freedom, 2015 sonrası ise operation freedom's sentinel kod adlarıyla adlandırılmıştır.\n\n7 ekim 2001'de abd'nin afganistan'ı istilası ile başlamış ve 30 ağustos 2021'de taliban'ın zaferi ile sonuçlanmıştır.\n\n2001'de ülkedeki taliban ve el-kaide eğitim kampları yok edildi. taliban, aldığı yenilgi sonrası 2003'te yeniden organize olarak isaf ve afgan hükümetine karşı bir ayaklanma başlattı. bu yeni ayaklanmada asimetrik savaş ı benimseyerek gerilla mücadelesi, pusular ve intihar bombası eylemlerini benimsedi. zamanla güney ve doğu afganistan'ın kırsal kesiminde etkisini artırdı. zamanla ülke genelinde şiddet arttı. 2011'de ülkedeki isaf askeri sayısı 140.000'e ulaştı. 2 mayıs 2011'de usame bin ladin öldürüldü. (bkz: usame bin ladin'in ölümü) temmuz 2013'te molla ömer öldü, mayıs 2016'da ise molla mansur öldürüldü. 2004-2018 arasında pakistan'daki örgütlere drone saldırıları yapıldı.\n\n2012'de nato liderleri savaştan çekilmeye ve gerisini afganistan yönetimine bırakmaya karar verdiler. 28 aralık 2014'te isaf dağıtıldı ve yerine resolute support mission kuruldu. 2018'den itibaren abd ve taliban katar'da barış üzerine müzakerelere başladı. 2020'de doha'da imzalan antlaşma sonrası abd ve diğer yabancı ülkelerin birlikleri afganistan'dan çekilmeye başladı. (bkz: abd'nin afganistan'dan çekilmesi) 2021'de çekilmenin hızlanmasıyla birlikte taliban 2021 taliban taarruzu'nu başlatıp 15 ağustos 2021'de pencşir haricinde ülkeyi ele geçirdi. (bkz: penşir direnişi) 30 ağustos 2021'de abd ve diğer ülkelerin çekilmesini tamamlaması ile birlikte savaş taliban zaferi ile sona erdi.\n\nhttps://en.wikipedia.org/…n_afghanistan_(2001–2021)\n\nhttps://tr.wikipedia.org/…nistan_savaşı_(2001-2021)\n\n(bkz: afganistan savaşları)\n(bkz: taliban ayaklanması)\n(bkz: afganistan barış süreci)",
      "referenced_content": [],
      "has_external_url": true
    },
    {
      "title": "afganistan savaşı",
      "entry_id": "102467941",
      "author": "jotaro",
      "date": "22.02.2020 16:43",
      "content": "(bkz: #102467918)",
      "referenced_content": [
        {
          "type": "entry",
          "title": "afganistan",
          "entry_id": "102467918",
          "author": "jotaro",
          "date": "22.02.2020 16:42",
          "content": "7 günlüğüne ateşkese giren ülke. ateşkesin başarılı olması durumunda abd ile taliban arasında çekilme antlaşması imzalanacak.\n\nhttps://www.trthaber.com/…lari-durdurun-462393.html",
          "has_external_url": true
        }
      ],
      "referenced_entry_ids": [
        "102467918"
      ],
      "has_external_url": false
    },
    {
      "title": "afganistan savaşı",
      "entry_id": "102803820",
      "author": "jotaro",
      "date": "29.02.2020 13:51 ~ 19:17",
      "content": "(bkz: #102803537)\n(bkz: 29 şubat 2020 taliban barış anlaşması)",
      "referenced_content": [
        {
          "type": "entry",
          "title": "afganistan-baris-sureci",
          "entry_id": "102803537",
          "author": "jotaro",
          "date": "29.02.2020 13:44",
          "content": "bugün doha'da barış antlaşmasının imzalanarak sonlanması planlanan süreç.\n\nhttps://www.aljazeera.com/…tan-200228055452287.html",
          "has_external_url": true
        }
      ],
      "referenced_entry_ids": [
        "102803537"
      ],
      "has_external_url": false
    },
    {
      "title": "afganistan savaşı",
      "entry_id": "103067642",
      "author": "jotaro",
      "date": "05.03.2020 17:17",
      "content": "(bkz: #103067632)",
      "referenced_content": [
        {
          "type": "entry",
          "title": "uluslararasi-ceza-mahkemesi",
          "entry_id": "103067632",
          "author": "jotaro",
          "date": "05.03.2020 17:16 ~ 03.09.2021 16:10",
          "content": "abd'nin, afganistan islam cumhuriyeti'nin ve taliban'ın afganistan savaşı'ndaki savaş suçlarını inceleyecek olan mahkeme.\n\nhttps://www.bbc.com/news/world-asia-51751717\n\nhttps://www.aa.com.tr/…-sorusturmasina-onay/1755528\n\nhttps://en.wikipedia.org/…estigation_in_afghanistan",
          "has_external_url": true
        }
      ],
      "referenced_entry_ids": [
        "103067632"
      ],
      "has_external_url": false
    },
    {
      "title": "afganistan savaşı",
      "entry_id": "112935005",
      "author": "jotaro",
      "date": "13.09.2020 16:56",
      "content": "(bkz: #112934998)",
      "referenced_content": [
        {
          "type": "entry",
          "title": "afganistan-baris-sureci",
          "entry_id": "112934998",
          "author": "jotaro",
          "date": "13.09.2020 16:56",
          "content": "afganistan islam cumhuriyeti ile taliban arasındaki kısmı da tam anlamıyla başlayan süreç\n\nhttps://www.aa.com.tr/…muzakereleri-basladi/1971156",
          "has_external_url": true
        }
      ],
      "referenced_entry_ids": [
        "112934998"
      ],
      "has_external_url": false
    },
    {
      "title": "afganistan savaşı",
      "entry_id": "121954822",
      "author": "jotaro",
      "date": "14.04.2021 19:57",
      "content": "(bkz: #121954527)",
      "referenced_content": [
        {
          "type": "entry",
          "title": "afganistan-baris-sureci",
          "entry_id": "121954527",
          "author": "jotaro",
          "date": "14.04.2021 19:47",
          "content": "(bkz: #121954450)\n\n24 nisan - 4 mayıs 2021 arasındaki görüşmelere türkiye'nin ev sahipliği yapacağı süreç.\n\nhttps://www.dw.com/…ın-tarihi-belli-oldu/a-57187812",
          "referenced_entry_ids": [
            "121954450"
          ],
          "has_external_url": true
        }
      ],
      "referenced_entry_ids": [
        "121954527"
      ],
      "has_external_url": false
    },
    {
      "title": "afganistan savaşı",
      "entry_id": "125530778",
      "author": "jotaro",
      "date": "09.07.2021 12:01",
      "content": "(bkz: abd'nin afganistan'dan çekilmesi)",
      "referenced_content": [],
      "has_external_url": false
    },
    {
      "title": "afganistan savaşı",
      "entry_id": "126813105",
      "author": "jotaro",
      "date": "12.08.2021 00:01",
      "content": "(bkz: 2021 taliban taarruzu)",
      "referenced_content": [],
      "has_external_url": false
    },
    {
      "title": "afganistan savaşı",
      "entry_id": "127073214",
      "author": "jotaro",
      "date": "18.08.2021 23:39 ~ 20.08.2021 10:22",
      "content": "15 ağustos 2021 itibari ile taliban zaferi ile sonuçlanan savaş. devamı için:\n\n(bkz: penşir direnişi)\n(bkz: penşir'in taliban'a karşı ayaklanması)",
      "referenced_content": [],
      "has_external_url": false
    },
    {
      "title": "afganistan savaşı",
      "entry_id": "127082954",
      "author": "bakalim",
      "date": "19.08.2021 09:18",
      "content": "(bkz: afganistan'da taliban'a karşı direniş başlaması)",
      "referenced_content": [],
      "has_external_url": false
    },
    {
      "title": "afganistan savaşı",
      "entry_id": "127210049",
      "author": "bakalim",
      "date": "22.08.2021 18:40 ~ 26.08.2021 20:22",
      "content": "yeni savaş türkiyede biraz daha poziyonları açığa çıkaracaktır. ezberci bazı izlamcılar talibana zafer atfedip övünmektedir. artık yeni yeni bazıları paştun kökenli talibanın aslında afgan islamı tarzı bir şey olduğunu dolayısıyla kuzeydeki tacik-özbek'lerin aleyhine olduğunu düşünüyor ve kuzey cephesinin bir an önce talibanın façasını çizmesini istiyor.\n\nmuhtemelen önümüzdeki dönemler kuzey ile talibanın iç savaşına sahne olacak. türkiyede koalisyon halindeki islamcılar ve türk milliyetçileri burdaki iç savaş karşısında bir tutum sınavına tabi olacaklar.\n\nöngörümüzü de bırakalım tabi. malum etnik aidiyet dini aidiyetten daha somut ve katı. yani etnik aidiyet galip gelecektir. sonuç olarak türkiyedeki islamcılar yine itin götüne girip çıkıp tutumlarını revize edip özbekçi olacaklardır.\n(bkz: talibanı heyecanla takip edip zaferine seviniyoruz)",
      "referenced_content": [],
      "has_external_url": false
    },
    {
      "title": "afganistan savaşı",
      "entry_id": "127348088",
      "author": "upperrd",
      "date": "26.08.2021 12:30 ~ 12:33",
      "content": "savaşın abd'ye maliyeti açıklanan resmi rakamlara göre 1 trilyon dolar ve 2.500 asker kaybı olduğu söyleniyor. gayri resmi rakamlara göre 2 trilyon dolar üzerinde olduğu söyleniyor. bu miktar üç beş dünya devi ülke haricindeki ülkelerin gsyih'den daha büyük bir miktar.",
      "referenced_content": [],
      "has_external_url": false
    },
    {
      "title": "afganistan savaşı",
      "entry_id": "149230330",
      "author": "recomax",
      "date": "14.02.2023 05:34",
      "content": "910 milyar dolara mal olmuş savaş.",
      "referenced_content": [],
      "has_external_url": false
    },
    {
      "title": "afganistan savaşı",
      "entry_id": "156393458",
      "author": "bilal reyiz",
      "date": "04.09.2023 02:24",
      "content": "(bkz: #156392970)",
      "referenced_content": [
        {
          "type": "entry",
          "title": "bilinen-en-sasirtici-tarihi-bilgi",
          "entry_id": "156392970",
          "author": "bilal reyiz",
          "date": "04.09.2023 02:05 ~ 10:04",
          "content": "abd'nin ırak savaşında savaşın görüntülerini canlı yayında neredeyse dakika dakika takip edebilmemize rağmen 2001'de 11 eylül'den hemen sonra taliban'ı indirmek için afganistan'da yaptığı operasyon kağıt üzerinde bir \"cia operasyonu\" olarak geçtiği için neredeyse hiç video kaydı olmaması.\n\n11 eylül saldırılarından 2 hafta sonra cia ajanı gary schroen ekibiyle beraber gizlice özbekistan üzerinden afganistan'a gitti. burada taliban karşıtı kuzey ittifakına bağlı aşiretlerle görüşen schroen ve ekibi sınırsız cephane, silah ve hava desteği sözü verdi. ayrıca kuzey ittifakına bağlı afganlara taliban hedeflerini tespit edip işaretlemeleri için lazer aygıtlar dağıtıldı. bu kişilerin lazer vericiyle işaretlediği taliban hedefleri vurulacaktı ve bir yandan da kuzey ittifakı harekete geçecekti. ilk etapta operasyona abd'nin hava kuvvetlerini saymazsak elit delta force birlikleri dışında hiçbir abd ordu mensubu katılmayacaktı. taliban'ın indirilmesinde toplamda 200-300 civarı amerikan askeri görev alacaktı.\n\nhava bombardımanı başladıktan sonra taliban'ın dağılması ve iktidarı kaybetmesi sadece birkaç hafta sürdü. amerikan ordusu afganistan'a büyük ölçüde kandahar ve kabil düştükten sonra girdi. bu yüzden bu operasyonla ilgili video kaydı yok denecek kadar azdır.\n\nbu arada operasyon sonrası cia'den emekli olan gary schroen'in afganistan'daki anılarını yazdığı bir kitap mevcut.",
          "has_external_url": false
        }
      ],
      "referenced_entry_ids": [
        "156392970"
      ],
      "has_external_url": false
    }
  ]
}