{
  "scrape_info": {
    "timestamp": "2025-11-11T18:24:19.185678",
    "total_entries": 41,
    "input": "beşşar esad'ın göçmenlerin evlerini elinden alması",
    "time_filter": null,
    "filters": [],
    "filter_external_urls": false
  },
  "entries": [
    {
      "title": "beşşar esad'ın göçmenlerin evlerini elinden alması",
      "entry_id": "78055450",
      "author": "kingoflions",
      "date": "14.06.2018 14:29 ~ 22:00",
      "content": "beşşar esad'ın çıkardığı 10 no'lu kanunun sonucu olacak hadise . olayı özetlemek gerekirse, suriye hükümeti yeni bir kanun çıkardı. bu kanuna göre, yeniden inşası planlanan bölgelerde ev sahibinin (akrabası veya avukatı da olabilir) 30 gün içinde evin kendisine ait olduğunu belirten belgeyle başvurarak kanıtlaması lazım. kanıtlanmadığı taktirde, devlet evin mülkiyetine sahip olacak. meselenin sorunlu kısmı şurası: şu anda suriye'nin dışında yaşayan milyonlarca göçmenin büyük bölümünün elinde (haberde %70 gibi bir orandan bahsediliyor) mülkiyetini kanıtlayacak bir belge yok. ayrıca, daha önce rejime muhalif bölgelerde yaşayanların ülkeye giriş yaptıkları taktirde tutuklanma veya öldürülme korkusu var. bunu bilen suriye hükümeti de çıkardığı bu kanunla muhalif olan göçmenlerin evlerini ele geçirerek bu insanların ülkeye dönüş ihtimalini ortadan kaldırmayı ve suriye'yi daha homojen bir demografik yapıya kavuşturmayı planlıyor. ortada başta türkiye olmak üzere suriyeli göçmenlerin yaşadığı tüm ülkelerin kesinlikle karşı çıkması gereken bir durum olduğundan paylaşmak istedim.\n\nedit: insan hakları örgütlerinden ve lübnan'dan gelen eleştiriler üzerine, evin mülkiyetini kanıtlamak için vatandaşlara verilen süre bir aydan bir yıla çıkarılmış. verdiği bilgi için çaylak hocanerdebe'ye teşekkür ederim.\n\nedit 2: ayrıca, gelen alakasız eleştiriler üzerine açıklama gereği duyuyorum. hayatım boyunca ne akp'ye oy verdim ne de ışid gibi insanlıkla alakası olmayan örgütleri destekledim. inanmayan geçmişte yazmış olduğum siyasetle ilgili entry'lere göz atabilir. sadece mevcut hükümete muhalif olsak da ülkemizin çıkarlarına ters düşen her türlü kararın karşısında olmamız gerektiğini düşünüyorum.\n\nkonuyla ilgili robert fisk'in yorumu;\n\n'' when wars end, the winners redraw the maps. that’s what the british and french did to the ottoman empire after the first world war. ıt’s what hitler did in eastern europe when he thought he was winning. and what the allies did after the second world war. ıt’s what the ısraelis did during the palestinian nakba (disaster). and what saddam did to kuwait after he invaded the emirate. but now a subtle twist. even before it’s won back all of syria, the assad regime is doing a little redrawing of its own. not of its national frontiers. but within its cities.\n\nfor the new law no 10 calls for what looks like mass property expulsion in those areas of the country which rebelled against the syrian government after 2011. even inside their borders, many syrians claim that it will strip tens of thousands of citizens of their homes – especially in those pulverised districts of the country’s big cities which have been turned into miniature stalingrads and dresdens by years of fighting. and it will benefit the regime – author of the law – since all unclaimed property will become the property of the state. ıs this the way to bring about the “reconciliation” which the russians, the syrian state itself and its supporters talk about so emotionally?\n\n“ıt’s true that syria has lost the best of its youth and its infrastructure,” bashar al-assad said last year, “…but on the other hand it has gained a more healthy and more homogenous society.” ıs this what law no 10 is supposed to achieve? for it effectively deprives anyone who has opposed the regime or is thought to have opposed the regime or relatives of those who have opposed the regime or relatives of those who are thought to have opposed the regime, from regaining their property. the system of doing this – and the machinery of the law – has a special and sinister touch all of its own.\n\nhere’s how it works. destroyed areas of syria are to be reorganised, developed and reconstructed. to prove your claim to property – damaged or destroyed – you must appear in person with your real estate documents within 30 days. clearly, nobody outside syria who opposes the government can do this – nor can those tens of thousands who live outside syria’s frontiers to evade the military draft who, in theory and probably in practice, face arrest warrants if they go home.\n\nı took this up with a senior figure in syria’s chamber of trade. no problem, he said. property holders may appoint others – relatives or lawyers – to prove their claim to property. and this is true. fourth-degree relatives – second cousins, for example – can make this claim within the same 30 days. but proxy authorisation requires a security clearance which is unlikely to be given if those second cousins are representing relatives who are on a “wanted” list. all this is before we confront the hopelessness of millions of syrians abroad whose documents of ownership were burned in their homes or in government buildings during the syrian war. ıf you don’t have your papers, how do you prove you own your land?\n\neven lebanon, whose government contains sympathisers of the syrian regime – the president is one of them – has publicly expressed criticism of law no 10 – mainly because their country hosts far more than a million syrian refugees who, like the palestinian refugees of 1948 and 1967 who fled to lebanon, may now never return home. ghassan hasbani, the lebanese health minister (and deputy prime minister) bluntly told a saudi television channel that many of the syrians in lebanon “have lost their identity papers and some are prevented – out of safety fears – from returning to the country they left, fearing persecution”.\n\nthe un refugee agency says that more than 11 million syrians have been displaced internally or to host countries during the war. according to the norwegian refugee council, more than 70 per cent of refugees lack basic identification papers. there are painful parallels here to the plight of the 1947/8 palestinians refugees and their families, who are deprived of their homes under ısrael’s 1950 absentee property law which effectively prevents any arab returning to his land inside present-day ısrael who was expelled, fled or who left the country after 29 november 1947.\n\ngebran bassil, the lebanese foreign minister, has received no reply to a letter he sent to his opposite number in damascus, walid moalem, and to the un secretary general, expressing his own concern. “the inability of the displaced to prove their ownership within the given period,” he wrote, “may cause them to lose their property and sense…of national identity, which deprives them of one of the main incentives for their return to syria.” not that lebanon is standing up for syria’s refugees; it just wants them to leave – and regards law no 10 as a severe disincentive since the legislation may deprive them of the homes they would go back to.\n\nhasbani’s objection is straightforward: the implementation of the new law and the time frame: why only 30 days to produce papers and claim ownership? for assad’s opponents, it’s much simpler. for them, the regime is trying to dispossess its largely sunni muslim opponents, rebuild the devastated areas in which they lived and then sell them off at vast profit. this, they say, is a form of sectarian ethnic cleansing since the government will inevitably allow its shia muslim allies, including the alawite minority, to live in the newly reconstructed areas.\n\nas far back as 2012, a syrian legislative decree (number 66) allowed the government in damascus to “redevelop areas of unauthorised housing and informal settlements [slums].” ın the same year, legislation 63 allowed the syrian finance ministry to seize the assets of people who fell under the counterterrorism law (again of 2012). but this law itself embraces the regime’s interpretation of what “terrorism” means. an opponent of the government? a critic of the regime? a civilian who turned to armed warfare when his home was attacked?\n\none widespread claim is that the law enables ıranians to take over the property of exiled syrians. by law, neither ıranians not any other foreigner can do so – but ıranian companies can own property if they join the reconstruction process, and so can russian companies. there are repeated rumours in syria itself that ıranian companies have bought hotels near the old city of damascus, along with apartments near the shiite sayyida zainab mosque in the city, a place of pilgrimage for ıranians and ıraqi shia. ın fact, syrians are more concerned about ıran’s financial aspirations in syria than they are about the ıranian revolutionary guard corps which so obsesses ısrael and the us – and which may number fewer than 3,000 men in the whole of syria.\n\nall countries, of course, try to clear away their war ruins. the reconstruction of rotterdam – blitzed by the luftwaffe in 1940 – began under german occupation. tens of thousands of ruined homes in syria cannot be repaired or “restored” because they are damaged beyond repair or, in some cases, unrecognisable to the owners who have returned to them. and the recapture of most major syrian cities gives the regime a chance to bulldoze the tens of thousands of illegally-built squats which surround damascus, homs and aleppo, the so-called “informal settlements” referred to in legislation 66. many of these slum structures were built by the destitute rural poor who flooded to the cities before the war after massive drought in the countryside, and who joined the armed and later ıslamist militias which tried to destroy assad.\n\nno legislation mentions why these young people were forced to build their slum homes – there was much wrong with the government’s rural policies before the war – nor how the buildings came to be constructed in the first place. syrians know that bribes were paid. but then who were the bribes paid to? you can see why the laws choose not to go too deeply into the origins of these banlieues.\n\nthere are contradictions. at least one regional governor has tried to persuade citizens to stay in their ravaged homes – and not to leave with the busloads of rebel fighters to ıdlib, the dustbin province of syria which will surely suffer its own fire and death in the months to come (unless russia persuades them to leave for turkey). talal al-barazi, the governor of homs, pleaded with its civilians not to travel away with the busloads of armed men escorted by the russian army en route to ıdlib or the turkish border last year. he climbed onto one bus and promised its passengers that they could stay, that they would not be arrested or punished – until a sunni cleric on the bus told al-barazi quietly that the ıslamist fighters had told the families they would be liquidated if they did not travel out of homs. al-barazi, it’s said, may well be the next syrian minister of reconciliation. but he will have a hard job after law no 10.\n\nso why the rush? why now, when the war is still far from over, is it necessary to throw this legislation at the poor and the refugees and the displaced? true, there is likely to be a reorganisation of the internal security services, the mukhabarat, when the conflict is over – word has it that they will be placed under the control of the interior ministry in damascus which might curb their often-freelance activities and brutality. and bashar al-assad knows that syria’s continued existence comes only because of the syrian army’s fighting abilities and the price it has paid – total military dead is now 87,000 – and with the help of the russians. after this sacrifice, the army will have a major role in the rebuilding of syria.\n\nso what is the purpose of law no 10? we’ve seen property confiscation in syria before. when it was part of nasser’s united arab republic (along with egypt), farms and plantations were nationalised, along with 23 private banks and other companies. the baathists did the same in 1963-65 on a bigger scale. most of the companies taken during this period collapsed under corruption and bad management.\n\nbut this was small scale compared to law no 10, which raises the all-important question of what kind of syria bashar al-assad wants to see after the bloodletting is over and the ıslamists are destroyed and all of syria restored to central government control. ıs this going to create the “more healthy society” of which he spoke last year? ı guess it comes down to a simple equation: bad laws do not create “reconciliation”. and laws don’t win wars. they can restart them.''",
      "has_external_url": true
    },
    {
      "title": "beşşar esad'ın göçmenlerin evlerini elinden alması",
      "entry_id": "78056906",
      "author": "le fougueux",
      "date": "14.06.2018 15:28",
      "content": "tabi mülteciler de almanya'dan kanada'dan avusturalya'dan vs vs suriye'ye dönmek için can atıyorlardı, bu karar hepsini derinden yaraladı.",
      "has_external_url": false
    },
    {
      "title": "beşşar esad'ın göçmenlerin evlerini elinden alması",
      "entry_id": "78058082",
      "author": "zafersproblemset",
      "date": "14.06.2018 16:17",
      "content": "mültecileri sonsuza kadar bize kitleyen hamleyi yapmış. adam işini biliyor.",
      "has_external_url": false
    },
    {
      "title": "beşşar esad'ın göçmenlerin evlerini elinden alması",
      "entry_id": "78059166",
      "author": "arnatuile",
      "date": "14.06.2018 17:01 ~ 19:36",
      "content": "şunu bile savunanlar çıktı. hem de türkiye’den savunuyor adam. suriyede bile değil. ulan 6 milyon insan terketmiş evini. hepsi mi terörist bunların?\n\nhepsi terörist olsa ortada ne suriye kalır ne rusya. kaldı ki bayağısıda kadın, çocuk, yaşlı.\n\nallah sırf siyaseten bile esedi savunacak kadar aşağılık bir hale düşürmesin insanı. düşmanımı bile.\n\nakp'nin suriye politikasını, suriyeli göçmenlerin ülkeyi düşüreceği durumu sabah akşam tartışalım. ama siz de şu esed'in bir hayvanoğlu hayvan olduğunu kabul edin önce.",
      "has_external_url": false
    },
    {
      "title": "beşşar esad'ın göçmenlerin evlerini elinden alması",
      "entry_id": "78059634",
      "author": "meurglyse",
      "date": "14.06.2018 17:20",
      "content": "ışid destekçilerini üzmüş kanun. yerinde bir karar vermiş esad.",
      "has_external_url": false
    },
    {
      "title": "beşşar esad'ın göçmenlerin evlerini elinden alması",
      "entry_id": "78059636",
      "author": "ketender tepetopuzu",
      "date": "14.06.2018 17:20",
      "content": "savaş işte..\nyıllar sonra bir babayiğit gelirse torunlara bu mülkler için tazminat talep etme hakkı verir.\nbizim kendi yönetimlerimiz benzer durumda neler neler yapmış..",
      "has_external_url": false
    },
    {
      "title": "beşşar esad'ın göçmenlerin evlerini elinden alması",
      "entry_id": "78059788",
      "author": "bomonti turrret kokusu",
      "date": "14.06.2018 17:27",
      "content": "ülkesindeki bütün çomarları diğer ülkelere başarıyla iteliyor. tebrik ettim hamlesini.",
      "has_external_url": false
    },
    {
      "title": "beşşar esad'ın göçmenlerin evlerini elinden alması",
      "entry_id": "78060255",
      "author": "portagas d ace",
      "date": "14.06.2018 17:45",
      "content": "lan adam olduğu gibi çaktı suriyelileri kaçtıkları ülkelere.",
      "has_external_url": false
    },
    {
      "title": "beşşar esad'ın göçmenlerin evlerini elinden alması",
      "entry_id": "78060267",
      "author": "kaz gelecek yerden tavuk esirgeyen insan",
      "date": "14.06.2018 17:46",
      "content": "yine göreceğim tepkileri bilerek olaya farklı açıdan bakacağım.\n\nsen suriye'nin bir vatandaşı olarak hükumet karşıtı olaylara karış, toplumun önemli bir kitlesini kapsayan bir isyan organize et.\n\ndaha sonra işler çığrından çıkınca pılını pırtını toplayıp ülkeden kaç, başka bir yere yerleş.\n\ndevlet savaştan zarar gören bölgelere yeniden yapılanma projeleri başlatsın, bir de senin keyfini mi beklesin? kusura bakmayın ama medeniyet seviyesi en yüksek devletler dahil hiçbir devlet bir projeyi başlatmak için birilerinin keyfini beklemez.\n\ntürkiye'de de buna benzer şekilde acele kamulaştırma kararları alınıyor.\n\nsiz de biliyorsunuz ki suriye'de süregelen savaş boyunca hiç zarar görmemiş şehirler, ve şehirlerde bölgeler var. belki de kanun buraları yeniden eski haline getirmek için yapıldı. aklı başında hiçbir hükumet ya da devlet sıcak savaşın devam ettiği yerlerde yeniden yapılanma politikası izlemez.\n\nkanun maddelerini içeren hiçbir içerik yok.\n\npeşin not: ortada hiçbir kanıt yokken ingiliz (bkz: batılı) bir yazarın makalesini referans alarak saldıracak olan yazarlar olursa çok fena yapıştırırım lafı. o batılı yazalar sizin düşündüğünüze paralel şeyler yazınca problem olmuyor da istemediğiniz şeyleri kaleme alınca \"ey batıı!\" diye başlıyorsunuz.",
      "has_external_url": false
    },
    {
      "title": "beşşar esad'ın göçmenlerin evlerini elinden alması",
      "entry_id": "78060387",
      "author": "amra",
      "date": "14.06.2018 17:50",
      "content": "esad kaçanların geri alınmayacağını defalarca açıklamıştı. şimdi iç savaş sonrası dağıtılacak olan ganimet belirlendi. 2019 yazında inşaat başlar. türk firmalar taşeronluk kapabilecek mi, ona bakalım.",
      "has_external_url": false
    },
    {
      "title": "beşşar esad'ın göçmenlerin evlerini elinden alması",
      "entry_id": "78060411",
      "author": "hotan",
      "date": "14.06.2018 17:50 ~ 18:56",
      "content": "cakala bak seen!\nulen tapu kadastro falan yok mu bu ulkede? eger esad amacina ulasir ve multecilerin suriye’deki varliklarina el konursa, suriyelilerin ulkelerine donmelerini gerektirecek bir sebep kalmaz ve olan yine bize olur diye dusunuyorum.",
      "has_external_url": false
    },
    {
      "title": "beşşar esad'ın göçmenlerin evlerini elinden alması",
      "entry_id": "78060584",
      "author": "hem isa hem jesus",
      "date": "14.06.2018 17:57",
      "content": "iyi hoş güzel yapmışta olan bize oldu.\nartık ülkemizden suriyeye gönderemeyeceğiz milyonlarca suriyeliyi.\nbarış olsa bile.",
      "has_external_url": false
    },
    {
      "title": "beşşar esad'ın göçmenlerin evlerini elinden alması",
      "entry_id": "78060605",
      "author": "hippie blues lady",
      "date": "14.06.2018 17:57",
      "content": "robert fisk yorumunu kim anlar aq?",
      "has_external_url": false
    },
    {
      "title": "beşşar esad'ın göçmenlerin evlerini elinden alması",
      "entry_id": "78060642",
      "author": "raskolnikov baltasi",
      "date": "14.06.2018 17:58",
      "content": "(bkz: uzman orospu çocuğu beşsar esad)",
      "has_external_url": false
    },
    {
      "title": "beşşar esad'ın göçmenlerin evlerini elinden alması",
      "entry_id": "78060689",
      "author": "dagdeniz",
      "date": "14.06.2018 18:00",
      "content": "savunulmaması gereken uygulama. bir tarafın yaptığı yanlışlar diğer tarafın yaptığı yanlışları olumlamaz, bu yapılan sadece savaş başladığında insanların içine serpilen nefretin daha da büyümesine yol açar. devletin istediği ispat zaten devletin tapu dairelerinde mevcuttur.\n\nancak şunu da not düşelim: esad'ın kararlarının doğru veya yanlış olmasından önce ülkeye cihatçıları sokan, onlara askeri eğitim veren, muhaliflere başta hiç destek vermeyen halep'e el-faruk, nusra, ışid gibi unsurları sokan ülkelere bakmıyorsanız orada bir sorun vardır. önce suriye'nin cihatçıların ve onları destekleyen ülkelerin esad'la karşılaştırılamayacağını kabul edin, sonra esad'ın verdiği kararları tartışırız (bu kısım üstteki bir giriye ithafen yazılmıştır).",
      "has_external_url": false
    },
    {
      "title": "beşşar esad'ın göçmenlerin evlerini elinden alması",
      "entry_id": "78060735",
      "author": "seffaffrench",
      "date": "14.06.2018 18:02",
      "content": "aynısını bizim devletten de bekliyorum madem ülkeden kaçmak ülke yönetimine böyle bi hak veriyor hodri meydan, şartların zorluğundan ötürü iltica edip gidenlerin evlerini alsınlar . burada esad’a hak veren orospu çocukları türkiye cumhuriyeti böyle bir hamle yaptığı zaman haktan hukuktan filan bahsederler lol.",
      "has_external_url": false
    },
    {
      "title": "beşşar esad'ın göçmenlerin evlerini elinden alması",
      "entry_id": "78061079",
      "author": "alvagen",
      "date": "14.06.2018 18:16",
      "content": "şu iki yüzlü sözlük yazarlarını sevemedim gitti. baya da var bunlardan. gerçekten dünyanın en aşşalık insan türleridir bunlar benim gözümde.\n\nşimdi bunu biz((bkz: türkiye)) yapsak ne faşistliğimiz kalır ne de diktatörlüğümüz.\n\navrupa hemen çökerdi \"demokrasi demokrasi\" diye. bunu kendine göre sevdiğin adam yapınca hoşunuza gidiyor. benim gözümde kim çocuk öldürdüyse katil odur.\n\nkatilleri severken dikkat edin...",
      "has_external_url": false
    },
    {
      "title": "beşşar esad'ın göçmenlerin evlerini elinden alması",
      "entry_id": "78061081",
      "author": "geyikli baba",
      "date": "14.06.2018 18:16",
      "content": "zeki adamın hareketi.\niyi iteledi valla bize.",
      "has_external_url": false
    },
    {
      "title": "beşşar esad'ın göçmenlerin evlerini elinden alması",
      "entry_id": "78061162",
      "author": "captain chop",
      "date": "14.06.2018 18:18",
      "content": "ulkesini savunmayip kacanlarin mali, mülkü olmaz. vatan uğrunda ölenlerin vatanidir.",
      "has_external_url": false
    },
    {
      "title": "beşşar esad'ın göçmenlerin evlerini elinden alması",
      "entry_id": "78061183",
      "author": "alanyali",
      "date": "14.06.2018 18:19",
      "content": "'beşşar esat mı yapmış o zaman doğrudur' diyecekler yazarlarımız..\nşahsın yaptığı son zulümdür.",
      "has_external_url": false
    },
    {
      "title": "beşşar esad'ın göçmenlerin evlerini elinden alması",
      "entry_id": "78061263",
      "author": "kindaasshole",
      "date": "14.06.2018 18:22",
      "content": "ülkemizdeki 4,5 milyon suriyeliyi bize kitleyen hamledir.\n\nakşama dünya lideri reisimiz çıkar eyyyy esad, sen kimsin der, 1,5 milyon suriyeli daha kitlerler 6 milyon suriyeli ile bu iş huzur içinde çözülür",
      "has_external_url": false
    },
    {
      "title": "beşşar esad'ın göçmenlerin evlerini elinden alması",
      "entry_id": "78061628",
      "author": "guest34",
      "date": "14.06.2018 18:35",
      "content": "2012 de yaklaşık 20 milyon olan nüfusun dörtte birini bize itelelemiş suriye devlet başkanının son icraatı.öyle göte böyle .... demiş kısaca.\nnüfus bilgisi için wikipedia ya bakın diycem lakin hala hangi akla hizmet için engelldir anlamak mümkün değil.",
      "has_external_url": false
    },
    {
      "title": "beşşar esad'ın göçmenlerin evlerini elinden alması",
      "entry_id": "78061660",
      "author": "bestern",
      "date": "14.06.2018 18:36",
      "content": "en çok mhp'lileri sevindirmesi gerekirken milliyetçilerin karşı çıktığı kanun.\n\niç savaş öncesinde halep’te 975 bin, humus’ta 835 bin, şam’da 460 bin, lazkiye’de 385 bin hama’da 350 bin, rakka’da 120 bin, dera’da 75 bin, tartus’ta 50 bin, kuneytra’da 50 bin idlip’te 25 bin ve diğer bölgelerde 175 bin türkmen yaşamaktaydı.\n\n2011 de başlayan iç savaş sonrası halep türkmen bölgesi önce ışid sonra pyd’nin kontrolü altında girdikten sonra türkmenler buradan zorla göç ettirildi. bayır-bucak dediğimiz lazkiye türkmen bölgesi’nin bayır köyleri boşaldı; rakka türkmen bölgesi işıd’in kontrolündedir. hama-humus türkmen bölgesinde yaşayan türkmenler etnik temizliğe maruz kalmıştır; köyleri ve toprakları ellerinden alınmıştır. suriye türkmenlerinin en büyük mağduriyeti burada yaşanmıştır.\n\netkili bir dış politika ve uzun vadeli komşuluk ilişkilerini düzenleyecek ikili anlaşmalar yoluyla esad'ın çıkarmış olduğu bu 10 numaralı kanun en çok türkmenlerin işine yarayacaktır. tabi bunun gerçekleşmesi için aklında kaç milyon ton beton ve demir kullanılacağını hesaplayan adamlar yerine, ülke çıkarları için 5 yıllık, 10 yıllık ve 25 yıllık stratejik plan yapan adamlar lazım.",
      "has_external_url": false
    },
    {
      "title": "beşşar esad'ın göçmenlerin evlerini elinden alması",
      "entry_id": "78061663",
      "author": "tarkkuus kapansson",
      "date": "14.06.2018 18:36",
      "content": "bizim hükümet esed'e kötülük yapayım derken yüzyılın kıyağını geçti. ne kadar işe yaramaz varsa esed kurtuldu bunlardan. şimdi mallarada çökecek. allah verdikçe veriyor esed'e...",
      "has_external_url": false
    },
    {
      "title": "beşşar esad'ın göçmenlerin evlerini elinden alması",
      "entry_id": "78061723",
      "author": "sagliginiz icin",
      "date": "14.06.2018 18:38",
      "content": "(bkz: yunanistan'a itelemek)",
      "has_external_url": false
    },
    {
      "title": "beşşar esad'ın göçmenlerin evlerini elinden alması",
      "entry_id": "78061874",
      "author": "dilci02",
      "date": "14.06.2018 18:43",
      "content": "diktatöre yakışan bir harekettir. çünkü insanların malına zorla el koyma diktatörlüğün doğasında vardır ve ekşiciler her zaman olduğu gibi \"benim diktatörüm iyidir\" modunda takılıyor, esed'in bu eylemini destekleyen entryi şukela modunda en üste taşıyor.\n\ninsanların akp'yi bırakmamasının sebebini çok uzakta aramamak lazım. akp'lileri çağırdığınız şey, akp'nin laciverti çünkü. hiç öyle özgürlükçü, demokratik nutuklar atmayın. gücü ele geçirince akp'den farklı davranmayacaksınız.",
      "has_external_url": false
    },
    {
      "title": "beşşar esad'ın göçmenlerin evlerini elinden alması",
      "entry_id": "78062196",
      "author": "eylul ayazi",
      "date": "14.06.2018 18:53",
      "content": "mantıklıdır, iyi etmiştir.\ndefolup gitmeli bu suriyeli araplar bak evleride yapılıyor..",
      "has_external_url": false
    },
    {
      "title": "beşşar esad'ın göçmenlerin evlerini elinden alması",
      "entry_id": "78062241",
      "author": "from notre dame",
      "date": "14.06.2018 18:54",
      "content": "suriye için güzel türkiye için hass... bir haberdir. geçmiş olsun.",
      "has_external_url": false
    },
    {
      "title": "beşşar esad'ın göçmenlerin evlerini elinden alması",
      "entry_id": "78062410",
      "author": "ovungec zeus",
      "date": "14.06.2018 19:00",
      "content": "göçmenler ifadesinin mülteciler olarak değiştirilmesi gereken başlık.",
      "has_external_url": false
    },
    {
      "title": "beşşar esad'ın göçmenlerin evlerini elinden alması",
      "entry_id": "78062597",
      "author": "tercante",
      "date": "14.06.2018 19:06",
      "content": "türkiye de artık ev sahibi olmaya başladıkları için sanıyorum türkiye deki mülteciler için pek önemli değildir.",
      "has_external_url": false
    },
    {
      "title": "beşşar esad'ın göçmenlerin evlerini elinden alması",
      "entry_id": "78062746",
      "author": "taksi kime",
      "date": "14.06.2018 19:11 ~ 19:13",
      "content": "ulkemizdeki suriyeli sığınmacıların vatanına dönmesi için fırsattır. devletimiz kesin dönüş yapanlara önayak olmalı ve maddi, manevi ve yasal destek vermelidir.",
      "has_external_url": false
    },
    {
      "title": "beşşar esad'ın göçmenlerin evlerini elinden alması",
      "entry_id": "78063402",
      "author": "meisys",
      "date": "14.06.2018 19:34",
      "content": "oysa hainlik yapmayıp, evlerinde kalıp çocuklarının bombardımanlardan dolayı kör olup şoka girmesini izlemeliydiler.",
      "has_external_url": true
    },
    {
      "title": "beşşar esad'ın göçmenlerin evlerini elinden alması",
      "entry_id": "78064321",
      "author": "le fougueux",
      "date": "14.06.2018 20:04 ~ 20:05",
      "content": "şaka maka o mültecilerin suriye'ye geri döneceğine ciddi ciddi inananlar var, çoğu da bizim hükümetin yanlısı.\n\nadam gitmiş belçika almanya kanada gibi gayrimüslim ülkelerin refah seviyesinin keyfini sürüyor, bunlar burada adamın arkasından suriye'ye gitmek istediğini iddia ediyorlar.\n\nbi zahmet önce batı ülkelerinde yaşayan akp'li göçmenleri geri getirin buraya ama tabi yemez\n\nmalum tebaanın zeka seviyesi.",
      "has_external_url": false
    },
    {
      "title": "beşşar esad'ın göçmenlerin evlerini elinden alması",
      "entry_id": "78064587",
      "author": "dogurankazan",
      "date": "14.06.2018 20:14",
      "content": "esad, suriye vatandaşlarının evlerine dönmelerini teşvik etmek için böyle bir kanun çıkarmış olmalı. ayrıca muhaliflerin tekrar geri dönüp barınması da engellenir.",
      "has_external_url": false
    },
    {
      "title": "beşşar esad'ın göçmenlerin evlerini elinden alması",
      "entry_id": "78065912",
      "author": "obiwan",
      "date": "14.06.2018 21:09 ~ 21:12",
      "content": "bu sözlükteki gerizekalı sayısının çok olduğunu biliyordum ama bu kadarını beklemiyordum.\n\nesed iyi yapmış diyenler türkiye için iyi yapmış demiyo sayın davarlar, adam kendisi için iyi yaptı. türkiye adamın umrunda mı? nerde hazırcı it kopuk var türkiye’ye geldi. çoğalmak için bebe bisküvisi yemeler, türkleri sınava sokar onları sokmayız diyen başbakanlar, dilenciliğin haddi hesabı yok zaten. bu adamlar ülkesine döner diyebilen herhangi bir görüşten adam var mı aranızda? ha bir de vatandaşlık veririz bunlara tertemiz işte.\n\n6 milyon adamın hepsi mi terörist veya yiyici denmiş. tamam, vatansever olup çocuğu, ailesi için türkiye’ye gelenler var diyelim. onlar için de adam silahlı muhalif olmadığı sürece gelip malına sahip çıksın, beraber yeniden kuralım ülkeyi demiş. vatansever olup tehlike olmadığını gören suriyeliler de ülkesine dönerse -ki zaten üretken kesim de bunlardır- bize bildiğin en işe yaramaz, sorunlu kısım kalacak. bizimkiler de üç beş oy daha alayım diye türkleri 2. hatta 3. sınıf vatandaş haline getirecek. bizde 5. sınıf vatandaş da olsa oy verecek mal çok çünkü.\n\nyani diyeceğim, esed’in yaptığı kendisi için çok stratejik bir karar. türkiye için mi? 24 haziranda güneş doğmazsa bokumuzda boğulmaya devam.",
      "has_external_url": false
    },
    {
      "title": "beşşar esad'ın göçmenlerin evlerini elinden alması",
      "entry_id": "78067015",
      "author": "elife meftun muellif",
      "date": "14.06.2018 21:51",
      "content": "asrın lideri reisimiz tüm suriyelilere toki'den ev vererek katil diktatör esed'in bu kirli oyununu elbet bozacaktır elhamdülillah.",
      "has_external_url": false
    },
    {
      "title": "beşşar esad'ın göçmenlerin evlerini elinden alması",
      "entry_id": "78071933",
      "author": "dr krasny",
      "date": "15.06.2018 00:19",
      "content": "avrupa onun yüzün hesabını yaparken, ülkesine hesapsızca 4 milyon mülteci alıp serbest bırakanlar düşünsün.",
      "has_external_url": false
    },
    {
      "title": "beşşar esad'ın göçmenlerin evlerini elinden alması",
      "entry_id": "78085278",
      "author": "elixiradonis",
      "date": "15.06.2018 13:09",
      "content": "iç savaş olmadığı halde türkiye’den s*ktir olup gitmek diye başlık açanların, entry girenlerin, ülkeden kaçma planları yapan ve yollarını arayanların, suriyelilerin suriye’deki katliamdan kaçıp gitmelerini vatan hainliğiyle suçladığı başlık. bir de esad güzellemesi yapmazlar mı, insanın kanı donuyor.\n\nadama sorarlar savaş olmadığı halde kaçıp gitmen ve planını yapman kaçıncı dereceden hainlik diye?",
      "has_external_url": false
    },
    {
      "title": "beşşar esad'ın göçmenlerin evlerini elinden alması",
      "entry_id": "78086021",
      "author": "prndmtn",
      "date": "15.06.2018 13:40",
      "content": "bizim hükümet sorgusuz sualsiz terörist fetöcülerin mallarına el koymadı mı? beşar esad da kendi ülkesine karşı ayaklanan teröristlere aynısını yapıyor. kaldı ki 1 sene süre vermiş gelin taşınmazlarınıza sahip çıkın diye. uluslararası hukukta demekki devletin böyle bir hakkı var. suçsuz olanlar gidip haklarını alacak suçluysan teröristsen elveda suriye",
      "has_external_url": false
    },
    {
      "title": "beşşar esad'ın göçmenlerin evlerini elinden alması",
      "entry_id": "78086563",
      "author": "lifequitin",
      "date": "15.06.2018 14:01",
      "content": "(bkz: şimdi sıçtık)",
      "has_external_url": false
    },
    {
      "title": "beşşar esad'ın göçmenlerin evlerini elinden alması",
      "entry_id": "173412398",
      "author": "61ts",
      "date": "08.03.2025 09:17",
      "content": "mezhepçilerin mutlu günleri.",
      "has_external_url": false
    }
  ]
}