{
  "scrape_info": {
    "timestamp": "2025-11-11T17:15:31.611695",
    "total_entries": 97,
    "input": "30 suriyelinin köpek gezdiren kadına saldırması",
    "time_filter": null,
    "filters": [],
    "filter_external_urls": false
  },
  "entries": [
    {
      "title": "30 suriyelinin köpek gezdiren kadına saldırması",
      "entry_id": "92315766",
      "author": "helallokma",
      "date": "08.07.2019 12:22",
      "content": "30 tane köpeğin köpek gezdiren kadına saldırması\ngidin de bi nefes alalım ya, bıktık.",
      "referenced_content": [],
      "has_external_url": false,
      "sentiment_numeric": 3,
      "categories": [
        "NEUTRAL"
      ]
    },
    {
      "title": "30 suriyelinin köpek gezdiren kadına saldırması",
      "entry_id": "92315881",
      "author": "moondeath",
      "date": "08.07.2019 12:25",
      "content": "rezalet",
      "referenced_content": [],
      "has_external_url": false,
      "sentiment_numeric": 3,
      "categories": [
        "NEUTRAL"
      ]
    },
    {
      "title": "30 suriyelinin köpek gezdiren kadına saldırması",
      "entry_id": "92315940",
      "author": "tavuk tuyune alerjisi olan horoz",
      "date": "08.07.2019 12:27",
      "content": "bunun sonu iç savaş arkadaş. bunu hala göremeyen siyasilere diyecek bir şey bulamıyorum.\n\nbu oc arapları doldur kamyonlara bırak sınırlarına ülkelerinde ne bok yiyorlarsa yesinler. hümanist arap seviciler de yanlarında gidebilir.",
      "referenced_content": [],
      "has_external_url": false,
      "sentiment_numeric": 1,
      "categories": [
        "HATE",
        "XENO"
      ]
    },
    {
      "title": "30 suriyelinin köpek gezdiren kadına saldırması",
      "entry_id": "92315946",
      "author": "commodore 64",
      "date": "08.07.2019 12:27",
      "content": "her gün bir başka bakan bunları yalarsa olacağı bu. götleri iyice kalktı. kaçarak terkettikleri ülkelerini bırakıp bizim memlekete sahip olmaya çalışıyorlar.",
      "referenced_content": [],
      "has_external_url": false,
      "sentiment_numeric": 1,
      "categories": [
        "HATE",
        "XENO"
      ]
    },
    {
      "title": "30 suriyelinin köpek gezdiren kadına saldırması",
      "entry_id": "92315953",
      "author": "imamihanife",
      "date": "08.07.2019 12:27",
      "content": "30 suriyelinin parkta ne işi var diyeceğim de, zaten en az nüfuslu aile 10 kişiden oluşuyor.",
      "referenced_content": [],
      "has_external_url": false,
      "sentiment_numeric": 1,
      "categories": [
        "HATE",
        "XENO"
      ]
    },
    {
      "title": "30 suriyelinin köpek gezdiren kadına saldırması",
      "entry_id": "92315977",
      "author": "nonameone",
      "date": "08.07.2019 12:27",
      "content": "anasını sikememiş mi mahalleli.",
      "referenced_content": [],
      "has_external_url": false,
      "sentiment_numeric": 1,
      "categories": [
        "NEUTRAL"
      ]
    },
    {
      "title": "30 suriyelinin köpek gezdiren kadına saldırması",
      "entry_id": "92315997",
      "author": "sakunosuke",
      "date": "08.07.2019 12:28",
      "content": "içişleri bakanı olacak varlıkta ortalama bir söröyölönönön söçö köröşmö oranı türkten yarıdan daha az desin arap sevici orospu çocukları",
      "referenced_content": [],
      "has_external_url": false,
      "sentiment_numeric": 1,
      "categories": [
        "HATE",
        "XENO"
      ]
    },
    {
      "title": "30 suriyelinin köpek gezdiren kadına saldırması",
      "entry_id": "92316028",
      "author": "abicimnediryani",
      "date": "08.07.2019 12:29",
      "content": "(bkz: suriyeli sığınmacılar için referandum yapmak)",
      "referenced_content": [],
      "has_external_url": false,
      "sentiment_numeric": 3,
      "categories": [
        "POLICY"
      ]
    },
    {
      "title": "30 suriyelinin köpek gezdiren kadına saldırması",
      "entry_id": "92316061",
      "author": "lowpoly",
      "date": "08.07.2019 12:30",
      "content": "bu olaylar, süleyman soylu'nun sebebiyet vermiş olduğu iç huzursuzluklardır.\n\nkayıtsız almıyorlarmış\n\nkayıtları varsa şahıslar bulunsun. hadi bakalım.",
      "referenced_content": [],
      "has_external_url": true,
      "sentiment_numeric": 2,
      "categories": [
        "POLICY"
      ]
    },
    {
      "title": "30 suriyelinin köpek gezdiren kadına saldırması",
      "entry_id": "92316158",
      "author": "yagmursevenadamm",
      "date": "08.07.2019 12:33",
      "content": "şu orospu çocuklarını doldurdular ülkeye uğraş dur şimdi. bir de itin teki utanmadan çıkıp suriyeli suç oranı çok az diyor.",
      "referenced_content": [],
      "has_external_url": false,
      "sentiment_numeric": 1,
      "categories": [
        "HATE",
        "XENO"
      ]
    },
    {
      "title": "30 suriyelinin köpek gezdiren kadına saldırması",
      "entry_id": "92316318",
      "author": "alp9",
      "date": "08.07.2019 12:38",
      "content": "allah için yollasınlar şunları memleketlerine bela oldular burada.",
      "referenced_content": [],
      "has_external_url": false,
      "sentiment_numeric": 1,
      "categories": [
        "HATE",
        "XENO"
      ]
    },
    {
      "title": "30 suriyelinin köpek gezdiren kadına saldırması",
      "entry_id": "92316353",
      "author": "mcleod",
      "date": "08.07.2019 12:39",
      "content": "suriyelilerin buraya sığınmacı olarak değil, bildiğin işgalci olarak geldiklerinin delili olay.\n\noldu yavrum, parkı da üzerinize yapalım isterseniz!",
      "referenced_content": [],
      "has_external_url": false,
      "sentiment_numeric": 1,
      "categories": [
        "HATE",
        "XENO"
      ]
    },
    {
      "title": "30 suriyelinin köpek gezdiren kadına saldırması",
      "entry_id": "92316359",
      "author": "peter pan sendromlu",
      "date": "08.07.2019 12:39 ~ 13:56",
      "content": "bence suriyede kalan suriyeliler çok mutlu. nerde gereksiz, dingil, cahil herif varsa buraya itelediler. savaş ayağına ülkelerindeki çöpleri boşalttılar. bundan 20 sene sonra türkiye suriyeden daha orta doğulu olacak ve oradakiler bize bakıp acıyacak.",
      "referenced_content": [],
      "has_external_url": false,
      "sentiment_numeric": 1,
      "categories": [
        "HATE",
        "XENO"
      ]
    },
    {
      "title": "30 suriyelinin köpek gezdiren kadına saldırması",
      "entry_id": "92316369",
      "author": "zeddahi",
      "date": "08.07.2019 12:39",
      "content": "polis, savcı,hakim, mahkeme kısacası adalet arıyoruz. bu 30 kişi -tüm aileleri ile beraber- toplum huzurunu bozmaktan derhal sınır dışı edilmeli.",
      "referenced_content": [],
      "has_external_url": false,
      "sentiment_numeric": 1,
      "categories": [
        "HATE",
        "XENO"
      ]
    },
    {
      "title": "30 suriyelinin köpek gezdiren kadına saldırması",
      "entry_id": "92316468",
      "author": "mekta",
      "date": "08.07.2019 12:42",
      "content": "bunlar daha iyi günlerimiz.\ntanım: iyi günlerimizde olan olay",
      "referenced_content": [],
      "has_external_url": false,
      "sentiment_numeric": 3,
      "categories": [
        "NEUTRAL"
      ]
    },
    {
      "title": "30 suriyelinin köpek gezdiren kadına saldırması",
      "entry_id": "92316540",
      "author": "serefsiz apandisit agrisi sizisi",
      "date": "08.07.2019 12:44",
      "content": "ya artık biraz daha olay çıkarırsa bu itler ben tek başıma dalacam bu hayvanlara.\nne lan bu sizden çektiğimiz bizim karımıza kızımıza kızkardeşlerimize yaptıklarınız şerefsizler.\nsiktir olun gidin bu ülkeden yada biz göndermesini biliriz.",
      "referenced_content": [],
      "has_external_url": false,
      "sentiment_numeric": 1,
      "categories": [
        "HATE",
        "CRIME"
      ]
    },
    {
      "title": "30 suriyelinin köpek gezdiren kadına saldırması",
      "entry_id": "92316560",
      "author": "sekizinci samuray",
      "date": "08.07.2019 12:44",
      "content": "çocuksa acıma büyüyecek, kadınsa acıma üreyecek. çok faşist ama çok gerçek. bizden nefret ederek büyüyecekler bizden nefret ederek üreyecekler.",
      "referenced_content": [],
      "has_external_url": false,
      "sentiment_numeric": 2,
      "categories": [
        "XENO"
      ]
    },
    {
      "title": "30 suriyelinin köpek gezdiren kadına saldırması",
      "entry_id": "92316691",
      "author": "devian",
      "date": "08.07.2019 12:49 ~ 12:50",
      "content": "o orospu çocuklarının bana denk gelmesini dilediğim hadise.\n\n1",
      "referenced_content": [],
      "has_external_url": true,
      "sentiment_numeric": 1,
      "categories": [
        "HATE",
        "CRIME"
      ]
    },
    {
      "title": "30 suriyelinin köpek gezdiren kadına saldırması",
      "entry_id": "92316704",
      "author": "holdenmcgroin",
      "date": "08.07.2019 12:49",
      "content": "suriyeli kanseri yuzunden ulkede artacak olaylardan birtanesi.\n\nbu ilkel arap toplulugundan hemen kurtulmamiz sart.\n\ncolune don arap",
      "referenced_content": [],
      "has_external_url": false,
      "sentiment_numeric": 1,
      "categories": [
        "HATE",
        "XENO"
      ]
    },
    {
      "title": "30 suriyelinin köpek gezdiren kadına saldırması",
      "entry_id": "92316721",
      "author": "dialago",
      "date": "08.07.2019 12:50",
      "content": "sayın soylu izleyince ne düşündüğünü merak ettim.",
      "referenced_content": [],
      "has_external_url": false,
      "sentiment_numeric": 3,
      "categories": [
        "NEUTRAL"
      ]
    },
    {
      "title": "30 suriyelinin köpek gezdiren kadına saldırması",
      "entry_id": "92316760",
      "author": "serkancandan365",
      "date": "08.07.2019 12:51",
      "content": "hak ettiğimiz davranış..",
      "referenced_content": [],
      "has_external_url": false,
      "sentiment_numeric": 3,
      "categories": [
        "NEUTRAL"
      ]
    },
    {
      "title": "30 suriyelinin köpek gezdiren kadına saldırması",
      "entry_id": "92316777",
      "author": "hukumrans",
      "date": "08.07.2019 12:51",
      "content": "süleyman soylu’ nun seçimden sonra kadına şiddet de meşrulaşır o zaman dediği konu bu mudur?",
      "referenced_content": [],
      "has_external_url": false,
      "sentiment_numeric": 3,
      "categories": [
        "NEUTRAL"
      ]
    },
    {
      "title": "30 suriyelinin köpek gezdiren kadına saldırması",
      "entry_id": "92316814",
      "author": "gecedusu",
      "date": "08.07.2019 12:52",
      "content": "dağdan geldik bağdakini kovuyoruzlar başladıı",
      "referenced_content": [],
      "has_external_url": false,
      "sentiment_numeric": 2,
      "categories": [
        "HATE",
        "XENO"
      ]
    },
    {
      "title": "30 suriyelinin köpek gezdiren kadına saldırması",
      "entry_id": "92316880",
      "author": "brvacasa",
      "date": "08.07.2019 12:54",
      "content": "git gide daha çok gün yüzüne çıkıyor bu gibi olaylar, yakında bu mültecileri kovmak gerek yoksa iç savaş çıkacak, suriler ve diğerleri olmak üzere",
      "referenced_content": [],
      "has_external_url": false,
      "sentiment_numeric": 1,
      "categories": [
        "HATE",
        "XENO"
      ]
    },
    {
      "title": "30 suriyelinin köpek gezdiren kadına saldırması",
      "entry_id": "92316947",
      "author": "renderman",
      "date": "08.07.2019 12:56",
      "content": "bu pisliklere artık nazi gibi mi yapalım acaba?\n\nbaşka türlü insanlığa faydaları olmaz. arapları bir türlü sevemedim maalesef.",
      "referenced_content": [],
      "has_external_url": false,
      "sentiment_numeric": 1,
      "categories": [
        "HATE",
        "XENO"
      ]
    },
    {
      "title": "30 suriyelinin köpek gezdiren kadına saldırması",
      "entry_id": "92316999",
      "author": "kul ahmedin ceketi",
      "date": "08.07.2019 12:57",
      "content": "şaşırtmış değildir. suriyelilerin neden olduğu problemlerden artık gına gelmeye başladı.",
      "referenced_content": [],
      "has_external_url": false,
      "sentiment_numeric": 1,
      "categories": [
        "HATE",
        "XENO"
      ]
    },
    {
      "title": "30 suriyelinin köpek gezdiren kadına saldırması",
      "entry_id": "92317004",
      "author": "darth risus",
      "date": "08.07.2019 12:57 ~ 13:00",
      "content": "normal olan durum.çer çöp mağaraları koru,sonra onlarda bizi........\ndiyecek bir şey yok s... siyasilerine.dogu ve güneydoğu illerinde durum daha vahim.oralarda oturan sığınmacılar genelde ösö ve isid militanlarının ya da sempatizanlarının aileleri.birak kapıdan sokmayı sınırın 1 km yakınına bile yaklaşmaması lazım\nayrıca herkes suriyelilerden dertli ama afganlar suriyelilerden daha tehlikeli.\n1)erkekleri taliban rejimi nedeni ile askerliğini\nsavaş şartlarında yapmış oluyor\n2)çoğu demokrasiyi tağut olarak görüyor.\n3)afganistan nedeni ile kavgaya karışmaya daha hevesli,psikolojileri var.cunku artık oturmuş kanıksanmış bir içsavaş psikolojilerine sahipler.\n4)özellikle gariban gibi olmayanları haşhaş ve bilimum uyuşturucu ticaretinde kullanıldıkları söyleniyor.el kaide nin felan en onemli geliri afganistan esrarı ve afyonu ise, bu gelenler içinde görece da ha az garip olanlarından(araba,dükkân sahibi vs..) escobar çıkma ihtimali yüksek...\n5)suriyeliler maganda sürüsü gibi keyfi gezerken,afganlar çete gibi hiyerarşik hareket ediyorlar....\nsonuç:hepsinin ben diyen,ayırım göstermeden küfür edebilecek bir yazar adayi",
      "referenced_content": [],
      "has_external_url": false,
      "sentiment_numeric": 1,
      "categories": [
        "HATE",
        "XENO"
      ]
    },
    {
      "title": "30 suriyelinin köpek gezdiren kadına saldırması",
      "entry_id": "92317006",
      "author": "kjswbdlkjfdlkj",
      "date": "08.07.2019 12:57 ~ 12:58",
      "content": "hep şikayet edilen pitbull, rotweiller, dogo gibi köpeklerin artık işe yarama zamanının geldiğini gösteren haber. alacaksın 3'er 5'er çıkacaksın parklara.",
      "referenced_content": [],
      "has_external_url": false,
      "sentiment_numeric": 3,
      "categories": [
        "NEUTRAL"
      ]
    },
    {
      "title": "30 suriyelinin köpek gezdiren kadına saldırması",
      "entry_id": "92317013",
      "author": "ortalama vatandas",
      "date": "08.07.2019 12:57",
      "content": "çok sürmez, suriye mafya sı olayı patlar. yıllar önce dedim bunu.\n\nhenüz tam palazlanamadılar, hepsi bu.",
      "referenced_content": [],
      "has_external_url": false,
      "sentiment_numeric": 1,
      "categories": [
        "HATE",
        "XENO"
      ]
    },
    {
      "title": "30 suriyelinin köpek gezdiren kadına saldırması",
      "entry_id": "92317014",
      "author": "rahmetli komodor",
      "date": "08.07.2019 12:57",
      "content": "sanki ülke çok nezih bir yerdi gibi bir de 5 milyon ithal at hırsızı getirdik ya, helal olsun. aynen hakettiği gibi yönetiliyor ülke aslında, ama keşke suriyelileri de cumhur ittifakı oy dağılımına göre dağıtabilsem semtlere ve şehirlere. %75 oy veren konya var mesela, onlar çok istemiş demek ki bu suriyelilerin gelmesini, oraya alalım arkadaşları.\n\nbu arada farkettiniz mi bilmiyorum da süleyman soylu, tc içişleri bakanından ziyade suriye dış işleri bakanı gibi çalışıyor. ona kalsa bütün bu hırı gürü çıkaran da türklerdir, malum suriyeli ve afganlar suç işlemeyen melaike kardeşlerimizmiş meğer.",
      "referenced_content": [],
      "has_external_url": false,
      "sentiment_numeric": 1,
      "categories": [
        "HATE",
        "POLICY"
      ]
    },
    {
      "title": "30 suriyelinin köpek gezdiren kadına saldırması",
      "entry_id": "92317016",
      "author": "siyayey",
      "date": "08.07.2019 12:57 ~ 26.07.2019 12:01",
      "content": "az kaldı az... çok az kaldı.\n\nbu şerefsizlerin sonu iyi olmayacak. büyük çatışma olacak. bu entry'i favoriye alabilirsiniz.\n\nbugün 30 kişi yarın 100, öbür gün 10 000.\n\nen fazla 1 sene veriyorum, belki de 1 ay içinde.\n\nbekleyin.\n\ntanım: ülke insanını kışkırtan suriyeli piçlerin yaşattığı olay.",
      "referenced_content": [],
      "has_external_url": false,
      "sentiment_numeric": 1,
      "categories": [
        "HATE",
        "CRIME"
      ]
    },
    {
      "title": "30 suriyelinin köpek gezdiren kadına saldırması",
      "entry_id": "92317018",
      "author": "tiriskadan nick",
      "date": "08.07.2019 12:57",
      "content": "iç savaş is loading... kürtlerle türkleri birbirine düşüremediler, ülkeyi medeniyetten nasibini almamış suriyelilerle doldurdular. muhteşem taktik.",
      "referenced_content": [],
      "has_external_url": false,
      "sentiment_numeric": 1,
      "categories": [
        "HATE",
        "XENO"
      ]
    },
    {
      "title": "30 suriyelinin köpek gezdiren kadına saldırması",
      "entry_id": "92317088",
      "author": "amandahanimis",
      "date": "08.07.2019 12:59",
      "content": "tr de polis ne iş yapar bir türlü anlamıyorum. çok gelişmiş olmasına gerek yok. normal bir ülkede polis bu suriyelileri alır, sorgular, içlerinden şiddete bulaşmış olanları tespit edip ülkelerine geri göndermek için işlemlere başlar. ama burada hayat aynen devam eder. polis sana bana kimlik sorar.",
      "referenced_content": [],
      "has_external_url": false,
      "sentiment_numeric": 2,
      "categories": [
        "POLICY"
      ]
    },
    {
      "title": "30 suriyelinin köpek gezdiren kadına saldırması",
      "entry_id": "92317129",
      "author": "cleora",
      "date": "08.07.2019 13:00",
      "content": "en sonunda normal varadaşları sokaklarda ava çıkaracaklar, istenilen bu mu. devlet bizi korumuyorsa biz kendimizi korumak zorunda kalacağız. çoğu kayıtsız bu böceklerin, eksildiklerini kimse fark etmez.",
      "referenced_content": [],
      "has_external_url": false,
      "sentiment_numeric": 1,
      "categories": [
        "HATE",
        "XENO"
      ]
    },
    {
      "title": "30 suriyelinin köpek gezdiren kadına saldırması",
      "entry_id": "92317240",
      "author": "savasuzun",
      "date": "08.07.2019 13:03",
      "content": "yakında parka da giremezsin derler.",
      "referenced_content": [],
      "has_external_url": false,
      "sentiment_numeric": 3,
      "categories": [
        "NEUTRAL"
      ]
    },
    {
      "title": "30 suriyelinin köpek gezdiren kadına saldırması",
      "entry_id": "92317256",
      "author": "imbalanced",
      "date": "08.07.2019 13:04 ~ 13:07",
      "content": "bu orospu çocuklarına önlem alınmazsa eğer, halk yakında kendi önlemini alacak. gidişat malesef bu yönde. en ufak bir saygısızlık, aşırılık gördüğünüzde tepki verin bu kansız, topraksız, vatansız piçlere... sessiz kalmayalım. sessiz kaldıkça tepenize daha da çıkacaklar. çünkü hiç bir manevi değeri olmayan, saygısız, eğitimsiz, hayvandan farkı olmayan, tuhaf bir ırk bunlar. başımıza sardığınız işe bakın, kime küfür edeceğini şaşırıyor insan. bu topraklar kanla kazanıldı. atalarımızın kanıyla. bu nasıl bir rahatlık, bol kepçeden gelip burda insanlarımızı rahatsız ediyorsunuz. yeter lan artık!",
      "referenced_content": [],
      "has_external_url": false,
      "sentiment_numeric": 1,
      "categories": [
        "HATE",
        "XENO"
      ]
    },
    {
      "title": "30 suriyelinin köpek gezdiren kadına saldırması",
      "entry_id": "92317309",
      "author": "chase",
      "date": "08.07.2019 13:06",
      "content": "ıcim kanayarak izledigim görüntülerdir. 2023e kadar da bir tanesini göndereceklerini sanmıyorum, bakalim sonumuz ne olacak?",
      "referenced_content": [],
      "has_external_url": false,
      "sentiment_numeric": 3,
      "categories": [
        "NEUTRAL"
      ]
    },
    {
      "title": "30 suriyelinin köpek gezdiren kadına saldırması",
      "entry_id": "92317333",
      "author": "uhhuhthismyshit",
      "date": "08.07.2019 13:06",
      "content": "şuna faşitlik vs diyenlerin ta ... faşistler gondiklesin sizi.",
      "referenced_content": [],
      "has_external_url": false,
      "sentiment_numeric": 3,
      "categories": [
        "NEUTRAL"
      ]
    },
    {
      "title": "30 suriyelinin köpek gezdiren kadına saldırması",
      "entry_id": "92317339",
      "author": "joaquinsanchez",
      "date": "08.07.2019 13:06",
      "content": "oradaki mahalleli bu orospu çocuklarının analarını sikmediyse yazık olmuş.",
      "referenced_content": [],
      "has_external_url": false,
      "sentiment_numeric": 1,
      "categories": [
        "HATE",
        "SEXUAL"
      ]
    },
    {
      "title": "30 suriyelinin köpek gezdiren kadına saldırması",
      "entry_id": "92317601",
      "author": "gezenvet",
      "date": "08.07.2019 13:13",
      "content": "köpeği ekosistemlerinde kendilerine rakip gördükleri için saldırganlaşan gruptur. doğal bir afet ile karşılaşmadıkları gelecek iki bin yıllık bir süreçte evrim’lerini tamamlayıp köpek ile aynı ortamda yaşayabilecek bir seviyeye geleceklerini neticesinde olayın çözüleceği kanatındayım",
      "referenced_content": [],
      "has_external_url": false,
      "sentiment_numeric": 1,
      "categories": [
        "HATE"
      ]
    },
    {
      "title": "30 suriyelinin köpek gezdiren kadına saldırması",
      "entry_id": "92317635",
      "author": "dorkkoyt",
      "date": "08.07.2019 13:14",
      "content": "bu olay belki suriyelerle alakalı gündeme gelen 100. olay ama adam halen tipik faşist yalanı diyor. tamam kardeş senin için rahatlayacaksa bu da faşistlerin yalanı",
      "referenced_content": [],
      "has_external_url": false,
      "sentiment_numeric": 2,
      "categories": [
        "XENO"
      ]
    },
    {
      "title": "30 suriyelinin köpek gezdiren kadına saldırması",
      "entry_id": "92317729",
      "author": "ainmosni",
      "date": "08.07.2019 13:16",
      "content": "birkaç yıl sonra akp iktidardan gideceğini anlarsa bakın nasıl kullanacaklar suriyelileri, hepsini silahlandırırlar ve türkiyenin her yerinde iç savaş çıkartırlar. zaten 15 temmuz darbesi olunca binlerce silah kayıp oldu, yakındır diyeyim.",
      "referenced_content": [],
      "has_external_url": false,
      "sentiment_numeric": 1,
      "categories": [
        "HATE",
        "XENO",
        "CRIME"
      ]
    },
    {
      "title": "30 suriyelinin köpek gezdiren kadına saldırması",
      "entry_id": "92317750",
      "author": "yuksek muhendisim ben",
      "date": "08.07.2019 13:17",
      "content": "akp doneminde gerceklesmistir.\n\nturkiye cumhuriyeti'nin su anki icisleri bakani'nin dunku aciklamasini tekrar edelim:\n\"suriyeliler'in suca karisma orani bizim kendi vatandaslarimizin yarisi kadar bile degil.\"\n\nyakin tarihimizde, uzak tarihimizde ya da herhangi bir tarihte kendi vatandasina bu kadar dusman olan baska bir zumre hatirlamiyorum.",
      "referenced_content": [],
      "has_external_url": false,
      "sentiment_numeric": 2,
      "categories": [
        "XENO",
        "HATE"
      ]
    },
    {
      "title": "30 suriyelinin köpek gezdiren kadına saldırması",
      "entry_id": "92317767",
      "author": "smokinle kopruden atlayan adam",
      "date": "08.07.2019 13:17 ~ 13:41",
      "content": "bu kaçıncı?\n\n3 afgan erkeğin 12 yaşında çocuğa tecavüz etmesi başlığı ile beraber değerlendirince ve mesela sadece birkaç bin suriyeli alan uk'ye kıyasla bizim 4 milyon suriyeli aldığımızı düşününce burada bir harakiri görüyorum.\n\nülkeye ekonomi ve hukuk alanlarında son 17 senede yapılanları zaten ülkenin kuyusunu kazmak olarak görüyordum (fırsat kaybı da cabası).\n\nama \" onlar bizim kardeşlerimiz \" temalı, ümmetçi anlayış ile ülkeye getirilen milyonlarca suriyeli, afgan ve pakistanlının artık ülkeyi mezara koyup üstüne toprak atmak olduğunu görebiliyorum.\n\nbunda iyi bir niyet şöyle olabilir:\nuzun vadede islam topluluğu yaratmak isteniyor olabilir ama bunun gerçekleşeceğine inanan insan spiderman'a falan da inanır... islam dünyası safsatasının ve islami yönetim ideolojisinin tamamen iflas ettiğini, başarısızlık timsali olduğunu görmek için daha ne yaşanması gerekir bilemiyorum.\n\nneticede, bunları yapan güruh suikastçi olarak başımıza gelmediyse veya kasti olarak ülkenin altını kazıyorsa da, her halükarda bu eylem ile ülkeyi orta doğu islam bataklığı na çevirmek çok kolay oldu.\n\nbu kadar mülteci kısa sürede ülkeden gönderilmezse sonuçlarını siz göreceksiniz (görüyorsunuz zaten), çocuklarınız çok daha ağır görecek. torunlarınız belki var bile olmayacak veya iğrenç koşullarda yaşayacak.\n\nnot: üzgünüm ama istinasız hepsini yollayacaksın, faşist diyenler de faşist desin gerçekten umurumda değil; ne düşündükleri önemli değil, halka rağmen halk için dediğimiz bu zaten. ümmetçilik zırvasıyla zehirlenen adama bir şey anlatılmaz. ortada somut gerçekler varken göremiyorsa açıklamakla zaman kaybetmemeli, çünkü zaman değerli.\n\nardından çok sıkı vize sistemi uygulayarak seçe seçe göçmen/mülteci alacaksın. (gönderdiklerimi tekrar değerlendirmeye alıp, komşularına falan sorarak geri çağırabilirsin.) göçmenlik sistemi çok sıkı olmalı. bu sistem; finlandiyalı, isviçreli, japon, lüksemburglu için de geçerli. ülkeye elini kolunu sallaya sallaya girmek ne demek? ahır mı burası?",
      "referenced_content": [],
      "has_external_url": false,
      "sentiment_numeric": 1,
      "categories": [
        "HATE",
        "XENO",
        "CRIME"
      ]
    },
    {
      "title": "30 suriyelinin köpek gezdiren kadına saldırması",
      "entry_id": "92317912",
      "author": "de pardayan",
      "date": "08.07.2019 13:21",
      "content": "ben de bu parkın orada oturuyorum. camım tam bu parka bakıyor. şişli'ye taşındığımdan beri insanlar orada köpeklerini gezdirirler. olay olduğu saatlerde maçka parkındaydık arkadaşlarla. bir şeyler yazacağım ayıp olacak. ulan kadınların şöyle iç rahatıyla dolaşacağı üç beş yer kaldı zaten bari onları temiz bırakın. denk gelsem bende... neyse onuda demek istemiyorum. eşim her gün önünden geçiyor. aklıma gelince bir şey yapacakları sinirden kuduruyorum. düşün lan yakamızdan.",
      "referenced_content": [],
      "has_external_url": false,
      "sentiment_numeric": 3,
      "categories": [
        "NEUTRAL"
      ]
    },
    {
      "title": "30 suriyelinin köpek gezdiren kadına saldırması",
      "entry_id": "92317942",
      "author": "olmamis insan formu",
      "date": "08.07.2019 13:22",
      "content": "savaştan kaçmak, hayatta kalmayı istemek tabi haktır ama ülkelerinden bacakları kıçlarına vura vura kaçanlar burda efelik yapıyor buda yavşaklıktır.",
      "referenced_content": [],
      "has_external_url": false,
      "sentiment_numeric": 1,
      "categories": [
        "HATE",
        "XENO"
      ]
    },
    {
      "title": "30 suriyelinin köpek gezdiren kadına saldırması",
      "entry_id": "92318010",
      "author": "tortillo",
      "date": "08.07.2019 13:23",
      "content": "bu ülkede yakinda suriyeli avi baslar demedi demeyin, devlet önlem almazsa bu isler cigirindan cikar cok insan ölür devlet o zaman müdahale dahi edemez söyleyeyim. cok gec olmadan önlem alinsin.",
      "referenced_content": [],
      "has_external_url": false,
      "sentiment_numeric": 2,
      "categories": [
        "XENO",
        "POLICY"
      ]
    },
    {
      "title": "30 suriyelinin köpek gezdiren kadına saldırması",
      "entry_id": "92318143",
      "author": "ekerci",
      "date": "08.07.2019 13:27",
      "content": "eksi sozlugun gercegin %10u yansittigini gosteren olaydir.\n\nburada herkes, asarim keserim bunu bana yapacaklar varya... gibi atip tutuyorlar. olay olunca da herkes izliyor.\n\nbu adamlar artik yerlestiler. en iyisi siz yeni bir yer bakmaya baslayin eger suriyelilerden kurtulmak istiyorsaniz. mesela, suriyeye gidin. orda bu kadar kafa kesecek adam kalmadi hepsi turkiyede artik",
      "referenced_content": [],
      "has_external_url": false,
      "sentiment_numeric": 1,
      "categories": [
        "HATE",
        "XENO",
        "CRIME"
      ]
    },
    {
      "title": "30 suriyelinin köpek gezdiren kadına saldırması",
      "entry_id": "92318180",
      "author": "maremostrum",
      "date": "08.07.2019 13:28",
      "content": "ula adamlar şu köpeklere verdiğiniz ilgi alakanın ondabirini bize de verin demeye çalışmasıdır.",
      "referenced_content": [],
      "has_external_url": false,
      "sentiment_numeric": 3,
      "categories": [
        "NEUTRAL"
      ]
    },
    {
      "title": "30 suriyelinin köpek gezdiren kadına saldırması",
      "entry_id": "92318273",
      "author": "buiyidimi",
      "date": "08.07.2019 13:29",
      "content": "çoğunluk henüz bizdeyken bunları kovduk kovduk, değilse bunlar ağzımıza sıçmaya devam edecekler. bu arada mahalledeki türkler nerdeymiş olay olurken 30 kişinin hakkından gelemiyorsak yazıklar olsun bize, şahsen mahallemde öyle birşey olsa karışmadan duramam.(bayanım)",
      "referenced_content": [],
      "has_external_url": false,
      "sentiment_numeric": 1,
      "categories": [
        "HATE",
        "XENO"
      ]
    },
    {
      "title": "30 suriyelinin köpek gezdiren kadına saldırması",
      "entry_id": "92318297",
      "author": "blackgry",
      "date": "08.07.2019 13:30",
      "content": "bunlar malesef daha iyi günlerimiz:(siz doldurmaya devam edin bu it kopuğu ülkeye, sayıları biraz daha artsın (gerçi kendileri de bu konuda harıl harıl çalışıyor, her ailede 4-5 çocuk) sayıca bizi bir yakalasınlar görün neler olacak.\n\nbizi ülkenize aldınız teşekkür ederiz diyeceklerine buranın sahibi gibi davranıyorlar.\n\nhiç derdimiz yokmuş gibi bunlarla uğraşacağız bi de",
      "referenced_content": [],
      "has_external_url": false,
      "sentiment_numeric": 1,
      "categories": [
        "HATE",
        "XENO"
      ]
    },
    {
      "title": "30 suriyelinin köpek gezdiren kadına saldırması",
      "entry_id": "92318304",
      "author": "psk 55",
      "date": "08.07.2019 13:30",
      "content": "pitbull gezdiren apaçi olsaydı böyle olmazdı muhtemelen gücü yeten yetene amk",
      "referenced_content": [],
      "has_external_url": false,
      "sentiment_numeric": 2,
      "categories": [
        "NEUTRAL"
      ]
    },
    {
      "title": "30 suriyelinin köpek gezdiren kadına saldırması",
      "entry_id": "92318327",
      "author": "zengin peachi",
      "date": "08.07.2019 13:31",
      "content": "öyle ya da böyle bu it sürülerini bataklıklarına postalayacağız",
      "referenced_content": [],
      "has_external_url": false,
      "sentiment_numeric": 1,
      "categories": [
        "HATE",
        "XENO",
        "CRIME"
      ]
    },
    {
      "title": "30 suriyelinin köpek gezdiren kadına saldırması",
      "entry_id": "92318406",
      "author": "svdaxi",
      "date": "08.07.2019 13:33",
      "content": "ilk olarak bu ve benzeri başlıklarda güya hümanist güya objektif yazıyormuş gibi görünüp de alenen akp'nin kurduğu mafya düzeninde yer alan magandaları savunan, suriyelileri savunup kendi halkına düşmanlık yapan bazı orospu çocukları var, onlara sesleniyorum, şu suriyelileri o kadar seviyorsanız alın birini evinizde besleyin, hem çok seviyorsunuz ya her gece bir iki posta dübürünüzü de döver sizi mutlu eder.\nolaya gelince ise hep söylüyorum, bu çöl maymunları bu ülkeye atılmış en büyük kazıklardan biridir. bunda emeği olan herkesin allah belasını versin. olayın mağduru arkadaşlara da çok geçmiş olsun ama bunlar son değil, artık daha sık yaşanacak benzeri şeyler. çünkü artık toplum yay gibi gerildi suriyelilere karşı. devlet bişey yapmazsa bu konuda, önümüzdeki dönemler kötü olaylara gebe.",
      "referenced_content": [],
      "has_external_url": false,
      "sentiment_numeric": 1,
      "categories": [
        "HATE",
        "XENO",
        "CRIME"
      ]
    },
    {
      "title": "30 suriyelinin köpek gezdiren kadına saldırması",
      "entry_id": "92318411",
      "author": "hizli ve ofkeli tosbaga",
      "date": "08.07.2019 13:33",
      "content": "bu tarz olaylarda iktidarın yanıtı hazır.\n\n\"onlar suriyeli değil esad'ın ajanları, suriyeliler ile aramızda olay çıkartıp huzursuzluk yaratmaya çalışıyor.\"\n\nböyle bir açıklama gelir bekleyin ve görün.",
      "referenced_content": [],
      "has_external_url": false,
      "sentiment_numeric": 2,
      "categories": [
        "POLICY",
        "XENO"
      ]
    },
    {
      "title": "30 suriyelinin köpek gezdiren kadına saldırması",
      "entry_id": "92318426",
      "author": "vatanmilletmersin",
      "date": "08.07.2019 13:33",
      "content": "olsun biz 15 temmuz'u suriyeliler sayesinde kazandık - soylu",
      "referenced_content": [],
      "has_external_url": false,
      "sentiment_numeric": 4,
      "categories": [
        "HUMAN",
        "HUMAN-POS"
      ]
    },
    {
      "title": "30 suriyelinin köpek gezdiren kadına saldırması",
      "entry_id": "92318427",
      "author": "transatlantik",
      "date": "08.07.2019 13:33 ~ 13:51",
      "content": "turkiye'nin yarisinin o kopegini gezdiren kadina degilde gecenin yarilarina kadar disarida kalabalik halde yayilip cekirdek citleyip ayaklarini karistiran araplara kendilerini daha yakin hissetmesi insanin kalbini paramparca ediyor.",
      "referenced_content": [],
      "has_external_url": false,
      "sentiment_numeric": 1,
      "categories": [
        "HATE",
        "XENO",
        "CRIME"
      ]
    },
    {
      "title": "30 suriyelinin köpek gezdiren kadına saldırması",
      "entry_id": "92318505",
      "author": "launcher",
      "date": "08.07.2019 13:34 ~ 13:38",
      "content": "hep onu gezdiriyorsunuz bizim neyimiz eksik diyen köpeklerin bir insana saldırısı.\n\nlafım saldıran tarafadır. ırkı beni ilgilendirmez. 30 türk köpek gezdiren bir suriyeliye de saldırsa farketmez.",
      "referenced_content": [],
      "has_external_url": false,
      "sentiment_numeric": 1,
      "categories": [
        "HATE",
        "XENO"
      ]
    },
    {
      "title": "30 suriyelinin köpek gezdiren kadına saldırması",
      "entry_id": "92318554",
      "author": "bohemburjuvas",
      "date": "08.07.2019 13:35",
      "content": "suriyelileri rahatsız ettiği gerekçesi ile köpek gezdiren kadına ceza kesilmese bari",
      "referenced_content": [],
      "has_external_url": false,
      "sentiment_numeric": 2,
      "categories": [
        "XENO",
        "POLICY"
      ]
    },
    {
      "title": "30 suriyelinin köpek gezdiren kadına saldırması",
      "entry_id": "92318623",
      "author": "md5 developer",
      "date": "08.07.2019 13:36",
      "content": "bu konular hakkında hükümet yetkililerin özellikle trabzonlu bir bakanımız ısrarla; suriyelilerin suç oranı türk vatandaşlarının suç oranından çok çok düşüktür demesi bizi kendi memleketimiz de bu konular da savunmaması ileri derece de sinir bozucu. misafir perverlik nedir bilmeyen insan silüetleri.",
      "referenced_content": [],
      "has_external_url": false,
      "sentiment_numeric": 2,
      "categories": [
        "POLICY"
      ]
    },
    {
      "title": "30 suriyelinin köpek gezdiren kadına saldırması",
      "entry_id": "92318640",
      "author": "ge ji kai",
      "date": "08.07.2019 13:37",
      "content": "bu gidişatın sonu iç savaş, siyasiler bunu nasıl ön göremiyor anlayamıyorum diyen arkadaşa ve onun gibi düşünen binlerce kişiye cevap niteliğinde: zaten amaçları bu olabilir mi acaba? bop eşbaşkanı haşmetlimizin amacı zaten bu ülkenin gerek demografik yapısını bozma gerekse siyasi kutuplar arası düşmanlık serpme yoluyla buna uğraşıyor olması gerçekten aklınıza hiç gelmiyor mu?",
      "referenced_content": [],
      "has_external_url": false,
      "sentiment_numeric": 2,
      "categories": [
        "POLICY"
      ]
    },
    {
      "title": "30 suriyelinin köpek gezdiren kadına saldırması",
      "entry_id": "92318697",
      "author": "john vattic",
      "date": "08.07.2019 13:38",
      "content": "ulan birileri köpek gezdiren kadına saldırıyor, birileri arabaların üzerinde zıplıyor, bunlar bu cesareti bulabiliyorsa ben hukuğun... neyse yeni küfrettim banlanmayayım sonra. birileri bir şey yapsın lan saldırganları salmayın artık doğru düzgün cezasını verin ben de bu ülkede yaşıyorum yarın sokağa çıkamayacak hale geleceğim bunlardan...",
      "referenced_content": [],
      "has_external_url": false,
      "sentiment_numeric": 2,
      "categories": [
        "CRIME"
      ]
    },
    {
      "title": "30 suriyelinin köpek gezdiren kadına saldırması",
      "entry_id": "92318777",
      "author": "sonsuztravma",
      "date": "08.07.2019 13:40",
      "content": "şuraya yazan, tepki gösterenlerin çoğu kendi sokakta köpeğe tahammül etmez, kendi gittiği parka sahiplisinin bile istemez, ama burda canavar kesilir... bizde köpeğini gezdirene, sokak hayvanı besleyene saldıran, sözlü taciz eden bir sürü dallama ve onlara çanak tutan \"biz de hayvan severiz...le başlayan cümleleri hayanları ölüm kamplarına tıkmakla tamamlayanlardan bolca yerli ve milli olarak var zaten...\nsuriyelilerin yaptığı her pisliği bizde onlardan önce de şimdi de yapanlar var, hatta nüfusa oranlar bizimkiler daha fazla... ama olsundu, hırsızsa bizim hırsızımız, sapıksa bizim sapığımız, magandaysa bizim magandamız nasılsa... suriyeliler de sanırsın keyiften geldiler, orayı cehenneme çeverinlerin silahları, lojistik desteği kimlerden aldığını bir zahmet düşünün, verdiğiniz vergilerle oradaki insanları öldürenlere tırlarla silah yollayıp, lider kadrosunu helikopterlerle getirdikleri hastanelerde tedavi ettirip bir de basına pozlar verenleri hatırlayın.\nsuriyeli burda kalmamak için ölümü göze alıyor çoluk çocuk, ege denizi bildiğiniz toplu mezara döndü...\nayrıca gelene neden geldin demek yerine, getirene, sebep olanlara sorun...\niki yüzlü olmayı da bırakın...",
      "referenced_content": [],
      "has_external_url": false,
      "sentiment_numeric": 1,
      "categories": [
        "HATE",
        "XENO",
        "CRIME"
      ]
    },
    {
      "title": "30 suriyelinin köpek gezdiren kadına saldırması",
      "entry_id": "92318887",
      "author": "elm sokagi sakini",
      "date": "08.07.2019 13:43 ~ 13:44",
      "content": "araplar köpek sevmez. bir keresinde katar’da bizi polisle parktan dışarı attırmışlardı köpek gezdirdiğimiz için. çocukları köpeğe musallat olup köpeği strese sokmuşlardı, “haram haram” diye bağırıp duruyorlardı. olayın bu nedenle kesinlikle yaşanmış olduğunu düşünüyorum. adamlar gelip bizim ülkemizi sahiplendi. çıldırmamak, isyan etmemek elde değil.",
      "referenced_content": [],
      "has_external_url": false,
      "sentiment_numeric": 1,
      "categories": [
        "HATE",
        "XENO"
      ]
    },
    {
      "title": "30 suriyelinin köpek gezdiren kadına saldırması",
      "entry_id": "92319008",
      "author": "muallimen",
      "date": "08.07.2019 13:46",
      "content": "artık kesinlikle gitmeleri gerekiyor yoksa çok daha büyük olaylara sebebiyet verecekler\nbelki sonu iç savaş bile olabilir",
      "referenced_content": [],
      "has_external_url": false,
      "sentiment_numeric": 1,
      "categories": [
        "HATE",
        "XENO",
        "CRIME"
      ]
    },
    {
      "title": "30 suriyelinin köpek gezdiren kadına saldırması",
      "entry_id": "92319157",
      "author": "songeneral",
      "date": "08.07.2019 13:49",
      "content": "bu çöl farelerini şımartanlar gurur duysunlar,yazıklar olsun.",
      "referenced_content": [],
      "has_external_url": false,
      "sentiment_numeric": 1,
      "categories": [
        "HATE",
        "XENO"
      ]
    },
    {
      "title": "30 suriyelinin köpek gezdiren kadına saldırması",
      "entry_id": "92319345",
      "author": "renginibellietmeyenbukalemun",
      "date": "08.07.2019 13:53",
      "content": "koskoca türk devletinde, türk halkını koruyacak bir türk yetkili yok mu acaba?",
      "referenced_content": [],
      "has_external_url": false,
      "sentiment_numeric": 3,
      "categories": [
        "POLICY"
      ]
    },
    {
      "title": "30 suriyelinin köpek gezdiren kadına saldırması",
      "entry_id": "92320284",
      "author": "killanan adam",
      "date": "08.07.2019 14:18",
      "content": "hayrettin karaca park ı'nda olmuş saldırıdır.\nbana uzak olduğu için şu an köpeklerimle oraya gitme şansım yok ama haftasonu üşenmeyip arabaya atlayacağım ve parkta köpeklerimle dolaşacağım. umarım o suriyeli lere denk gelirim.",
      "referenced_content": [],
      "has_external_url": false,
      "sentiment_numeric": 1,
      "categories": [
        "HATE",
        "XENO"
      ]
    },
    {
      "title": "30 suriyelinin köpek gezdiren kadına saldırması",
      "entry_id": "92320292",
      "author": "serotoningibiadam",
      "date": "08.07.2019 14:19",
      "content": "ülkesini savunmaya götü yemeyen orul orul orospu çocuklarının soysuzların bir yerde sayıca çok olunca kadına saldırmaları artistlik yapma durumdur. bunları savunanlarda bunlardan farklı değildir",
      "referenced_content": [],
      "has_external_url": false,
      "sentiment_numeric": 1,
      "categories": [
        "HATE",
        "XENO",
        "CRIME"
      ]
    },
    {
      "title": "30 suriyelinin köpek gezdiren kadına saldırması",
      "entry_id": "92321042",
      "author": "qappaq",
      "date": "08.07.2019 14:36",
      "content": "ülkemde yabancı istemiyorum, suriyeli hiç!..",
      "referenced_content": [],
      "has_external_url": false,
      "sentiment_numeric": 1,
      "categories": [
        "HATE",
        "XENO"
      ]
    },
    {
      "title": "30 suriyelinin köpek gezdiren kadına saldırması",
      "entry_id": "92322250",
      "author": "einbeos",
      "date": "08.07.2019 15:05",
      "content": "türk milletine iyi oluyor aq hak ediyoruz bu koduğumun arapları tarafından aşağılanmaya",
      "referenced_content": [],
      "has_external_url": false,
      "sentiment_numeric": 1,
      "categories": [
        "HATE",
        "XENO"
      ]
    },
    {
      "title": "30 suriyelinin köpek gezdiren kadına saldırması",
      "entry_id": "92322348",
      "author": "henip",
      "date": "08.07.2019 15:07",
      "content": "lan bu kadar geri zekalılık olur mu?!\n\nistenmediğiniz yerde ırkçılık damarını kabarta kabarta ne olacağını sanıyorsunuz siz?!\n\ncidden şanslarını zorluyorlar...\n\nbu topraklarda birinin üç şeyine dokunmayacaksın:\n-sevdiğine\n-kazancına\n-mülküne\n\nbunlara dokunmaya kalkmak sadece delilik...",
      "referenced_content": [],
      "has_external_url": false,
      "sentiment_numeric": 2,
      "categories": [
        "HATE",
        "XENO"
      ]
    },
    {
      "title": "30 suriyelinin köpek gezdiren kadına saldırması",
      "entry_id": "92322508",
      "author": "heroftheworld",
      "date": "08.07.2019 15:12",
      "content": "malesef sonu iç savaş ben bunu görüyorum kim ne derse desin bu kaçınılmaz.tarihten ibret almayın siz yine aynı tarihi yaşarsınız.tarihte göçler olmuştur fakat nüfusun yapısını değiştiren göçler ülkelerin parçalanmasıyla sonuçlanmıştır .bunları geri göndermek artık mümkün değil en az 100 yıllık sorunumuz var vatana millete hayırlı olsun.",
      "referenced_content": [],
      "has_external_url": false,
      "sentiment_numeric": 1,
      "categories": [
        "XENO",
        "POLICY"
      ]
    },
    {
      "title": "30 suriyelinin köpek gezdiren kadına saldırması",
      "entry_id": "92322556",
      "author": "at gomer",
      "date": "08.07.2019 15:13",
      "content": "ya abi ülkenin gençlerine hitman usulü verin destek size 1 haftada huzurlu bir ortam verelim ya artık yeter ya",
      "referenced_content": [],
      "has_external_url": false,
      "sentiment_numeric": 3,
      "categories": [
        "CRIME"
      ]
    },
    {
      "title": "30 suriyelinin köpek gezdiren kadına saldırması",
      "entry_id": "92323130",
      "author": "7714714",
      "date": "08.07.2019 15:27",
      "content": "akp nin eseri",
      "referenced_content": [],
      "has_external_url": false,
      "sentiment_numeric": 3,
      "categories": [
        "POLICY"
      ]
    },
    {
      "title": "30 suriyelinin köpek gezdiren kadına saldırması",
      "entry_id": "92323392",
      "author": "vadrigar",
      "date": "08.07.2019 15:34",
      "content": "(bkz: çare kıyma makinesi)",
      "referenced_content": [],
      "has_external_url": false,
      "sentiment_numeric": 3,
      "categories": [
        "NEUTRAL"
      ]
    },
    {
      "title": "30 suriyelinin köpek gezdiren kadına saldırması",
      "entry_id": "92323470",
      "author": "emirjordan",
      "date": "08.07.2019 15:37 ~ 15:40",
      "content": "hükümetin suriye politikasının eseri.. bravo sayın yöneticiler, gerçekten bravo..\nbu daha başlangıç,\nyakın zamanda sokakta yürüyemez hale gelicek bizim insanımız.\nsınırda bir bölge oluştursaydılar, içeriye almasaydılar ve yardımlarını öyle devam ettirseydiler şu anda böyle sıkıntılar çekmiyorduk. ama berbat bir dış politika yüzünden durum böyle bir hal aldı. şimdi güvenli bölge denilmesi hiç bir şey ifade etmiyor, artık istediğiniz yapın zorlasanız da gitmezler.",
      "referenced_content": [],
      "has_external_url": false,
      "sentiment_numeric": 2,
      "categories": [
        "POLICY",
        "XENO"
      ]
    },
    {
      "title": "30 suriyelinin köpek gezdiren kadına saldırması",
      "entry_id": "92324364",
      "author": "intrigante",
      "date": "08.07.2019 15:58 ~ 30.05.2020 17:34",
      "content": "konuyu tam olarak okumadım, yorumum da yok fakat suriyelilerin neden kendi aralarında türkçe küfürleştiklerini anlamadım. metinde “bağırarak küfrediyorlar.” denmiş de onların küfür olduğu nasıl anlaşılmış, suriyeliler kendi aralarında türkçe mi konuşuyor? anlayan varsa açıklayabilir mi?\n\nedit: suriyeli olduğu öne sürülen şahıslar kadına “köpeğinin kakasını buradan al.” demişler, kadın da “ben aldım, o başkasınınkidir.” demiş, tartışma öyle çıkmış. üsttekiyle birlikte açıklanmayan yerler var gibi.",
      "referenced_content": [],
      "has_external_url": false,
      "sentiment_numeric": 3,
      "categories": [
        "NEUTRAL"
      ]
    },
    {
      "title": "30 suriyelinin köpek gezdiren kadına saldırması",
      "entry_id": "92324707",
      "author": "feedleme arwen",
      "date": "08.07.2019 16:06",
      "content": "kendi ülkesi gibi rahat rahat dolaşmıyolar mı bi de aq suriyelileri.\n\ngidin lan istemiyoruz sizi ne yüzsüz iğrenç varlıklarsınız. çocuklarınıza aşı yaptırmazsınız eski hastalıkları yeniden canlandırırsınız erkekleriniz 5 para etmez bütün gün nargile içip kız kesmekten başka kadınlar da üreyeyim türeyeyim kafasında çocuklarınız yerlerde sürünüp milletten para dilenir daha neler neler\n\ngidin artık siktirin gidin",
      "referenced_content": [],
      "has_external_url": false,
      "sentiment_numeric": 1,
      "categories": [
        "HATE",
        "XENO",
        "CRIME"
      ]
    },
    {
      "title": "30 suriyelinin köpek gezdiren kadına saldırması",
      "entry_id": "92326587",
      "author": "redcity",
      "date": "08.07.2019 16:54",
      "content": "referandum talep eden insanlar var inanilmazsiniz,beyfendilere hanfendilere bi de referandum mu yapıcaz???",
      "referenced_content": [],
      "has_external_url": false,
      "sentiment_numeric": 3,
      "categories": [
        "POLICY"
      ]
    },
    {
      "title": "30 suriyelinin köpek gezdiren kadına saldırması",
      "entry_id": "92328420",
      "author": "hgzr",
      "date": "08.07.2019 17:38",
      "content": "arkadaşlar, işinize gelince izinli ve sayıyla işçi olarak türkiye'den istenen insanları örnek gösteriyorsunuz ya.\n\nbu oksimoron bir örnek ama insan olduğu için sonuçları doğru. bugün almanya'da kahvede sosyal yardım alan ve almanlara söven türkler varsa, ingiltere'de şeriat okulu açıp yine de işid'e katılan araplar varsa, suriye'den alınan bu kadar insanla da zihinsel koğuşlar olacaktır.\n\nki burası almanya değil ne beşeri sermaye ne de başka yönden. burada çiçek çocukluk yaparak insanları sustursanız bile olacakları engelleyemezsiniz. almanya'daki türkleri örnek veriyorsunuz ya, oraya bir daha bakıp bunu da anlayın .",
      "referenced_content": [],
      "has_external_url": false,
      "sentiment_numeric": 2,
      "categories": [
        "HATE",
        "XENO"
      ]
    },
    {
      "title": "30 suriyelinin köpek gezdiren kadına saldırması",
      "entry_id": "92328494",
      "author": "ecrof",
      "date": "08.07.2019 17:40",
      "content": "yazın iyice azıyor bu suriyeliler...",
      "referenced_content": [],
      "has_external_url": false,
      "sentiment_numeric": 2,
      "categories": [
        "HATE",
        "XENO"
      ]
    },
    {
      "title": "30 suriyelinin köpek gezdiren kadına saldırması",
      "entry_id": "92328511",
      "author": "ozt",
      "date": "08.07.2019 17:40",
      "content": "ipi sapı olmayan, götü boklu ortadoğulu insan müsveddelerinin gerçekleştirmiş olduğu orospu çocukluğu. din kardeşi zırvalarıyla memlekete doldurulan bela makineleri bunlar. kayıt dışı girenlerin hepsi toplanıp sınır dışı edilmeli. kayıtlı olanlar da denetim altında tutulmalı. birden fazla şikayet yiyen, sabıkası olan kim varsa hepsi sınır dışı edilmeli. sosyal yardımlar türkiye vatandaşlarına uygulananlarla eşit olmalı, fazlası yapılmamalı. sadece en az beş yıl bu topraklarda çalışmış, vergilerini eksiksiz ödemiş ve hiçbir suç işlememiş kişiler ülkemizden vatandaşlık alabilme hakkına sahip olabilmeli. bunların ya da bunlara benzer kararların alınması gerek artık. geç bile kalındı ama yanlış yolun neresinden dönülse kardır.",
      "referenced_content": [],
      "has_external_url": false,
      "sentiment_numeric": 2,
      "categories": [
        "HATE",
        "XENO",
        "POLICY"
      ]
    },
    {
      "title": "30 suriyelinin köpek gezdiren kadına saldırması",
      "entry_id": "92328658",
      "author": "bozukbaykus",
      "date": "08.07.2019 17:44",
      "content": "amk suriyelileri",
      "referenced_content": [],
      "has_external_url": false,
      "sentiment_numeric": 1,
      "categories": [
        "HATE",
        "XENO"
      ]
    },
    {
      "title": "30 suriyelinin köpek gezdiren kadına saldırması",
      "entry_id": "92328714",
      "author": "deveyehendekatlatanadam",
      "date": "08.07.2019 17:45",
      "content": "ya tamam sevmiyoruz bu mk maymunlarını da kaynak nedir? o tweetler mi? baya güvenilirmiş!",
      "referenced_content": [],
      "has_external_url": false,
      "sentiment_numeric": 1,
      "categories": [
        "HATE",
        "XENO"
      ]
    },
    {
      "title": "30 suriyelinin köpek gezdiren kadına saldırması",
      "entry_id": "92328815",
      "author": "livefreeordie",
      "date": "08.07.2019 17:48",
      "content": "yeter artık şu suriye'lilere güzel bir yaptırım kararı çıkartılmalı.\n\ngündemde kalması gereken bir konudur. bir değil iki değil bir şekilde çözülmesi gereken bir konudur.\n\n(bkz: orospu çocuğu araplar)",
      "referenced_content": [],
      "has_external_url": false,
      "sentiment_numeric": 2,
      "categories": [
        "HATE",
        "XENO",
        "POLICY"
      ]
    },
    {
      "title": "30 suriyelinin köpek gezdiren kadına saldırması",
      "entry_id": "92328889",
      "author": "kotu talihli esek",
      "date": "08.07.2019 17:50",
      "content": "daha büyük ve kanlı olaylara vesile olacak olaydır.\nşu videodaki ortamın ülkemiz sınırları içinde oluşmuş olması bile başlı başına elim bir olaydır. zaten halihazırda bir çok sorunla başa çıkmaya çalışan insanlarımızın artık gecenin bir vaktinde, karanlıkta, nereden neyin geleceğini bilmediği bir ortamda insan avına çıkması korkutucu bir durumdur. bir arbede yaşanması, kavga çıkması durumunda birçok insana yazık olur ve sonucunda hiçbir caydırıcı önlem alınmaz ki böyle bir şey bile çok saçma olurdu çünkü bu tür olayların başlamadan önlem alınması gerekir, bu önlem de ülkedeki tüm arapların ve hümanist arap sevicilerin toplanıp sınır dışına çıkarılmasıdır.",
      "referenced_content": [],
      "has_external_url": false,
      "sentiment_numeric": 1,
      "categories": [
        "HATE",
        "XENO",
        "POLICY"
      ]
    },
    {
      "title": "30 suriyelinin köpek gezdiren kadına saldırması",
      "entry_id": "92329230",
      "author": "delafuente",
      "date": "08.07.2019 17:59",
      "content": "ülkenin huzuru için, göçmenlerden suça karışanların sınır dışı edilmesi gerekiyor. aksi takdirde böyle kaygısızca saldırmaya yüz bulmaya devam edecekler.",
      "referenced_content": [],
      "has_external_url": false,
      "sentiment_numeric": 2,
      "categories": [
        "POLICY",
        "XENO"
      ]
    },
    {
      "title": "30 suriyelinin köpek gezdiren kadına saldırması",
      "entry_id": "92329947",
      "author": "orle",
      "date": "08.07.2019 18:20",
      "content": "gün gelecek, bu savaştan kaçan ama sığındığı ülkede her türlü arsızlığı yapmaktan çekinmeyen suriyeliler, yağmurdan kaçarken doluya tutulmak neymiş görecekler.. şanslarını fazla zorlamasınlar bence.",
      "referenced_content": [],
      "has_external_url": false,
      "sentiment_numeric": 2,
      "categories": [
        "HATE",
        "XENO"
      ]
    },
    {
      "title": "30 suriyelinin köpek gezdiren kadına saldırması",
      "entry_id": "92330055",
      "author": "yatacakyerimyok",
      "date": "08.07.2019 18:23",
      "content": "suç işleme oranları türklerden azmış, öyle diyor ss. aptallığı meşrulaştırmaya çalışmak bu olsa gerek.",
      "referenced_content": [],
      "has_external_url": false,
      "sentiment_numeric": 2,
      "categories": [
        "HATE",
        "XENO"
      ]
    },
    {
      "title": "30 suriyelinin köpek gezdiren kadına saldırması",
      "entry_id": "92331181",
      "author": "euphratesss",
      "date": "08.07.2019 18:50 ~ 19:00",
      "content": "almanlarin ahi cikiyor",
      "referenced_content": [],
      "has_external_url": false,
      "sentiment_numeric": 3,
      "categories": [
        "NEUTRAL"
      ]
    },
    {
      "title": "30 suriyelinin köpek gezdiren kadına saldırması",
      "entry_id": "92332944",
      "author": "orta suvari",
      "date": "08.07.2019 19:38 ~ 20:17",
      "content": "burada başlık olarak yazılması gereken 30 kişinin köpek gezdiren kadına saldırması.milliyet bildirmenin fazladan bir değer katması bekleniyorsa başka tabii.",
      "referenced_content": [],
      "has_external_url": false,
      "sentiment_numeric": 2,
      "categories": [
        "HATE",
        "XENO"
      ]
    },
    {
      "title": "30 suriyelinin köpek gezdiren kadına saldırması",
      "entry_id": "92334428",
      "author": "heroftheworld",
      "date": "08.07.2019 20:16",
      "content": "zavallı ülkem 6 milyon mülteciye kurban edildi malesef elimiz kolumuz bağlı kimse anlamıyor yada anlamak istemiyor.durumun ciddiyetinin farkında değil yazık yazık.",
      "referenced_content": [],
      "has_external_url": false,
      "sentiment_numeric": 2,
      "categories": [
        "HATE",
        "XENO"
      ]
    },
    {
      "title": "30 suriyelinin köpek gezdiren kadına saldırması",
      "entry_id": "92352465",
      "author": "susak kabagi",
      "date": "09.07.2019 04:31",
      "content": "iç savaş olmaz iç katliam olur.\n80 milyona 3 milyon suriyeliler için bir yok oluş olur.\ntürk insanı değişik bir karaktere sahip.\nrakıyı ver sevsin damarına bas miksin.",
      "referenced_content": [],
      "has_external_url": false,
      "sentiment_numeric": 1,
      "categories": [
        "HATE",
        "XENO",
        "POLICY"
      ]
    },
    {
      "title": "30 suriyelinin köpek gezdiren kadına saldırması",
      "entry_id": "92376907",
      "author": "pirayjr",
      "date": "09.07.2019 18:19",
      "content": "hepsine yallah",
      "referenced_content": [],
      "has_external_url": false,
      "sentiment_numeric": 2,
      "categories": [
        "XENO",
        "HATE"
      ]
    },
    {
      "title": "30 suriyelinin köpek gezdiren kadına saldırması",
      "entry_id": "122569528",
      "author": "binkereolsemyinedonerim",
      "date": "29.04.2021 13:21",
      "content": "hadi iktidarın mülteci politikası belli de, bir tane muhalefet partisi de çıkıp diyemiyor ki “bana oy verin mültecileri ülkelerine yollayayım.” çözüm umudu olmayan sorunlarımızdan biri de bu mülteci konusu. daha binlerce var ve iktidardan geçtim dediğim gibi muhalefetin de çözüm önerisi / vaadi yok.",
      "referenced_content": [],
      "has_external_url": false,
      "sentiment_numeric": 3,
      "categories": [
        "POLICY"
      ]
    },
    {
      "title": "30 suriyelinin köpek gezdiren kadına saldırması",
      "entry_id": "122569620",
      "author": "bikalemgerek",
      "date": "29.04.2021 13:24",
      "content": "(bkz: #122460521) şu başlıkta 17 yaşındaki çocuğa acıyan hümanistler ne düşünüyor acaba, kendilerinin yorumlarını merak ediyorum. sonuçta bu 30 kişide bir zamanlar 17 yaşında çocuklardı, şimdi büyüdüler ve mesken tutuyorlar. bunlara acimamayi bu şekilde öğreneceksiniz.",
      "referenced_content": [
        {
          "type": "entry",
          "title": "suriyeli-multeciyi-tekme-tokat-doven-alman",
          "entry_id": "122460521",
          "author": "speciale aperta",
          "date": "26.04.2021 19:39 ~ 23:09",
          "content": "suriyeli mültecilerden bizler de şikayetçiyiz, hatta büyük bir bela bu durum. cahil, tembel ve vurdumduymaz insanlar bize hiçbir şey veremez, sadece düzen bozar. asıl beka sorunu işte budur! ama bu eski hükümlü alman'ın yaptığı faşizm ötesi ve kabul edilemez bir durum.\n\n17 yaşındaki çocuğa saldırıp tükürecek kadar ne oluyor? terbiyesiz herif...",
          "has_external_url": false
        }
      ],
      "referenced_entry_ids": [
        "122460521"
      ],
      "has_external_url": false,
      "sentiment_numeric": 2,
      "categories": [
        "HATE",
        "XENO"
      ]
    }
  ]
}