{
  "scrape_info": {
    "timestamp": "2026-02-07T21:59:55.731945",
    "total_entries": 27,
    "input": "beyin yakan pakistanlı çocuklar",
    "time_filter": null,
    "filters": [],
    "filter_external_urls": false
  },
  "entries": [
    {
      "title": "beyin yakan pakistanlı çocuklar",
      "entry_id": "113377127",
      "author": "kyrleechamasher",
      "date": "23.09.2020 12:59",
      "content": "adam olucak cocuklar videosu ve videodaki gergin oldugu kadar bozuntuya da vermeyen politik sunucu sehar kamran esliginde keyifli dakikalar.",
      "has_external_url": true
    },
    {
      "title": "beyin yakan pakistanlı çocuklar",
      "entry_id": "113377578",
      "author": "dukkanin ortasinda bagiran kosnuk",
      "date": "23.09.2020 13:14 ~ 13:15",
      "content": "sunucusu ikbal gürpınar olan ve hindistanı destroy etmek isteyen bebeler içeren video.\n\n(bkz: allahüekber wohooo)",
      "has_external_url": false
    },
    {
      "title": "beyin yakan pakistanlı çocuklar",
      "entry_id": "113377624",
      "author": "haciz mahallinde tango",
      "date": "23.09.2020 13:15",
      "content": "o kadar ay lav pakistaaaaaan ise niye gelip burada bizi darlıyorsunuz lan?",
      "has_external_url": false
    },
    {
      "title": "beyin yakan pakistanlı çocuklar",
      "entry_id": "113377700",
      "author": "tayyarahmet",
      "date": "23.09.2020 13:17",
      "content": "tatlılar lan. maşallah.",
      "has_external_url": false
    },
    {
      "title": "beyin yakan pakistanlı çocuklar",
      "entry_id": "113377712",
      "author": "fc korozyon",
      "date": "23.09.2020 13:17 ~ 15:46",
      "content": "pakistan is in the bag diye dolanmama sebep olan videodur.\n\nyalnız dikkatimi çeken bir şey daha var. çocuklar o yaşta ingilizce konuşabiliyor ve cümle kurabiliyorlar. ben o yaşlardayken hey sexy lady'den başka cümle kuramıyordum.\n\nyeşillendirme editi: eksi ingiltere sömürgesi altında olduklarındanmış bu ingilizce seviyesi. yeşillendiren dostlara teşekkür ederim. ayrıca eğitim dilleride ingilizceymiş.",
      "has_external_url": false
    },
    {
      "title": "beyin yakan pakistanlı çocuklar",
      "entry_id": "113377874",
      "author": "bin984",
      "date": "23.09.2020 13:21",
      "content": "videonun içeriğinden bağımsız olarak bir yorum yapmak istiyorum. türkiye’deki yaşıtlarından ve hatta bazı büyüklerinden çok daha ileri düzeyde ingilizceleri var ve özgüvenli bi şekilde konuşabiliyorlar.",
      "has_external_url": false
    },
    {
      "title": "beyin yakan pakistanlı çocuklar",
      "entry_id": "113378025",
      "author": "demetrius of magnesia",
      "date": "23.09.2020 13:25",
      "content": "aklıma 2 şey getiren video;\n\n1. neden o kadar bağırıyorlar?\n2. bu çocukların büyüyünce de bizden daha mutlu hissedecek olmasına biraz içerledim.",
      "has_external_url": false
    },
    {
      "title": "beyin yakan pakistanlı çocuklar",
      "entry_id": "113378077",
      "author": "karin desen jackin karni",
      "date": "23.09.2020 13:26 ~ 13:40",
      "content": "durup dururken i love pakistan diye bağırmaya vesile olacak video.\n(bkz: pakistan ülkü ocakları)",
      "has_external_url": false
    },
    {
      "title": "beyin yakan pakistanlı çocuklar",
      "entry_id": "113378159",
      "author": "kuyrukrotoru",
      "date": "23.09.2020 13:29",
      "content": "son derece takdir ettiğim çocuklar.\n\nvideodaki giyimi kuşamı atmosferi bir kenara bırakırsak, sunucunun \"ilerde ne olmak istiyon\" sorusuna, çocukların tamamı pakistan için yapacaklarını söylemiş. gerçi bir tanesi gaza gelip \"hindistan ın amına goyacaam\" demiş ama onuda heyecanına verebiliriz.\n\nbizim burada, hemde 23 nisan törenlerinde, canlı yayında böyle bir soruya \"çalışıp liseyi/üniversiteyi okumak için almanya ya amerikaya gidip orada yaşayacam\" diyor çocuklar.",
      "has_external_url": false
    },
    {
      "title": "beyin yakan pakistanlı çocuklar",
      "entry_id": "113378325",
      "author": "jack of shades",
      "date": "23.09.2020 13:33 ~ 13:35",
      "content": "yarim saat sonra bunlardan iki yas buyuk cocuklara ”will\" ile cumle kurdurmaya calisacagim. keske ”i will be a pilot” diye ciglik atabilseler. turkce okurken bile tekliyorlar\n\ngulun eglenin ama bizden egitim anlaminda birkac fersah ileride olan cocuklardir",
      "has_external_url": false
    },
    {
      "title": "beyin yakan pakistanlı çocuklar",
      "entry_id": "113378461",
      "author": "kuradilammas",
      "date": "23.09.2020 13:36",
      "content": "haydi hindistan'i ucuralim insallah.",
      "has_external_url": false
    },
    {
      "title": "beyin yakan pakistanlı çocuklar",
      "entry_id": "113378836",
      "author": "korkunun ta kendisi",
      "date": "23.09.2020 13:46",
      "content": "video o kadar gaza getirici ki, balkona çıkıp \"i love pakistaaaannnn\" diye bağırasım geldi.",
      "has_external_url": false
    },
    {
      "title": "beyin yakan pakistanlı çocuklar",
      "entry_id": "113378841",
      "author": "hatir hutur havatir",
      "date": "23.09.2020 13:47",
      "content": "milliyetçilik böyle bir şey değil arkadaşım. bu çocuklar gerçekten milliyetçi olsalardı ve o duygularla yetiştirilselerdi hindistan'ı yok etmek yerine hindistan'la birleşmek isterlerdi. aynı dili konuşan, aynı toprakların çocukları niye birbirlerine düşman? niye bunu bozuk bir ingilizce ile dile getiriyorlar? sen önce bunu sor kendine. hiç mi kafanda bir ışık çakmıyor?",
      "has_external_url": false
    },
    {
      "title": "beyin yakan pakistanlı çocuklar",
      "entry_id": "113378978",
      "author": "reeon",
      "date": "23.09.2020 13:50",
      "content": "uzun zaman sonra iyi güldüm",
      "has_external_url": false
    },
    {
      "title": "beyin yakan pakistanlı çocuklar",
      "entry_id": "113379237",
      "author": "vulgaris magistralis",
      "date": "23.09.2020 13:58",
      "content": "kendilerini patlatacaklarmış da, talibanmış da...\n\nülkemi yolsuzluktan kurtarıp, diğer ülkelerden aşağı olmadığımızı göstereceğim diyen çocuklara karşı neden bu öfke?\n\nbizdeki benzer törenlerde küçük çocuklara çığlık atar gibi şiir okutturan eğitimciler yok mu sanki?\n\nvideo ile ilgili düşünceniz vatan sevgisi diye çocuklara hindistan düşmanlığı ve kin aşılandığı yönünde ise ifadenizi o yönde düzenleyin, her müslüman çocuğuna terörizmi yakıştırmayı bırakın.\n\nayrıca, (bkz: pakistan zindabad)",
      "has_external_url": false
    },
    {
      "title": "beyin yakan pakistanlı çocuklar",
      "entry_id": "113379371",
      "author": "normalinsa",
      "date": "23.09.2020 14:02 ~ 14:04",
      "content": "videodan pakistan’ın pekte barışçıl bir devlet olmadığı açık ve net anlaşılıyor. çocukların şiddete eğilimli bir eğitim aldıkları ve bu yönde pekiştirildikleri de net. ne var videoda diyen olmuş şiddet telkini, çocuk istismarı, ırkçılık kısacası ne ararsan kardeşim.",
      "has_external_url": false
    },
    {
      "title": "beyin yakan pakistanlı çocuklar",
      "entry_id": "113379415",
      "author": "tantunizade murat efendi",
      "date": "23.09.2020 14:03",
      "content": "karaçi merkez imam hatip ortaokulu yıl sonu gösterisinde görev alan çocuklardır.",
      "has_external_url": false
    },
    {
      "title": "beyin yakan pakistanlı çocuklar",
      "entry_id": "113379788",
      "author": "alakasiz biri",
      "date": "23.09.2020 14:14 ~ 14:16",
      "content": "andımız okutulan çocuklarla aynı kaderi paylaştıklarını görmek için japon olmaya gerek yoktur.\n\nbir apaçi ağlıyor gözleri yaşlı",
      "has_external_url": true
    },
    {
      "title": "beyin yakan pakistanlı çocuklar",
      "entry_id": "113379795",
      "author": "sobrella",
      "date": "23.09.2020 14:14",
      "content": "altyazı mükemmel olmuş:d beyin yıkama nasıl olur buyrun hep beraber izleyelim.",
      "has_external_url": false
    },
    {
      "title": "beyin yakan pakistanlı çocuklar",
      "entry_id": "113379816",
      "author": "axxileas",
      "date": "23.09.2020 14:15",
      "content": "aralarında vatanını en çok sevenin gelecekte avrupa'ya diğerlerinden önce kaçak giriş yapmaya çalışacağı çocukları içeren video. ab'ye ulaşamadı, türkiye oldu; o da olumlu.",
      "has_external_url": false
    },
    {
      "title": "beyin yakan pakistanlı çocuklar",
      "entry_id": "113379852",
      "author": "peder zickler",
      "date": "23.09.2020 14:16 ~ 14:18",
      "content": "(bkz: pakistan in da butt)\n(bkz: my pledge is that i will be a pilot)\n(bkz: and help everyböl)\n(bkz: no one will have carrot)\n(bkz: grape)\n(bkz: wooow grape)\n\ngibi meme'ler ile haftalardır beyinlere kazınıp haklı bir başarıya ulaşmış tiktok şaheseri. tek kelimeyle özetleyecek olursak: graaape.\n\nhttps://www.youtube.com/watch?v=mxcbacbx-60",
      "has_external_url": true
    },
    {
      "title": "beyin yakan pakistanlı çocuklar",
      "entry_id": "113380299",
      "author": "himalayalardan gelen mucize",
      "date": "23.09.2020 14:28",
      "content": "o kadar etkiledi ki beni az önce evrak getiren vatandaşa ı will be a pilot ı love pakistan dedim ama neyse ki o cocuklar gibi ingilizce bilen bir millet olmadığımız için anlamadı...",
      "has_external_url": false
    },
    {
      "title": "beyin yakan pakistanlı çocuklar",
      "entry_id": "113380433",
      "author": "gucci mane",
      "date": "23.09.2020 14:31",
      "content": "eksi’nin muadilleri arasinda ne kadar geride\nkaldigini gosteren video.\n\nreddit’in yabanci sublarini gectim turk sublari burdurland, kgbtr, turkey jerky’de bile 3 aydir paylasilan bir video.",
      "has_external_url": false
    },
    {
      "title": "beyin yakan pakistanlı çocuklar",
      "entry_id": "113381023",
      "author": "senyour",
      "date": "23.09.2020 14:47",
      "content": "pakistanlı olmaktan aldığım tadı başka hiçbir şeyden almadım. belki bilardo.. ama yok lan pakistanlı olmak daha güzel.",
      "has_external_url": false
    },
    {
      "title": "beyin yakan pakistanlı çocuklar",
      "entry_id": "113381103",
      "author": "bufalobill",
      "date": "23.09.2020 14:49",
      "content": "milliyetçilik adı altında çocukların beyinlerini zehirliyorlar.",
      "has_external_url": false
    },
    {
      "title": "beyin yakan pakistanlı çocuklar",
      "entry_id": "113386944",
      "author": "yazaroldedilerolduk",
      "date": "23.09.2020 17:18",
      "content": "başlık kısa sürede milliyetçilik düşmanlarına ev sahipliği yapmaya başlamış. hatta kimileri işi andımıza kadar getirmiş. milliyetçiliğe düşman olmadan \"iyi de aga bunlar neden ingilizce konuşuyor?\" deseydiniz birçok şeyin cevabını kendi içinizde bulabilirdiniz.\n\nbir kürtün kürdüm demesi, ermeninin ermeniyim demesi, arabın arabım demesi normal ben türküm deyince ouvv",
      "has_external_url": true
    },
    {
      "title": "beyin yakan pakistanlı çocuklar",
      "entry_id": "139332667",
      "author": "tylor",
      "date": "28.06.2022 16:59",
      "content": "efsaneyi yeniden hatırlamak için.\n\nzıpkın gibi yetişen übersonik paki gençler.",
      "has_external_url": true
    }
  ]
}