{
  "scrape_info": {
    "timestamp": "2026-02-07T22:06:23.098720",
    "total_entries": 13,
    "input": "pakistanlıların elinden telefonu almak",
    "time_filter": null,
    "filters": [],
    "filter_external_urls": false
  },
  "entries": [
    {
      "title": "pakistanlıların elinden telefonu almak",
      "entry_id": "137184337",
      "author": "suanbuanoan",
      "date": "08.05.2022 15:14",
      "content": "sınırdan koşarak ve yürüyerek geçen pakistanlıları tek sıra haline alıp cevahir alışveriş merkezi girişine koyulan xr cihazlarından geçirirsek ve o sırada telefonlarını ellerinden alırsak bu sapıklık son bulabilir.\ntanım: sapıklık yapan mültecilere karşı geliştirdiğim çözümdür",
      "has_external_url": false
    },
    {
      "title": "pakistanlıların elinden telefonu almak",
      "entry_id": "137184602",
      "author": "umuttepeli",
      "date": "08.05.2022 15:22",
      "content": "bir soruna yönelik geliştirildiği iddia edilen düşük bütçeli bir çözüm.\nşaka desen değil. ciddi desen mümkün değil.\ndostum bu uzay meselesi böyle bir şey değil.",
      "has_external_url": false
    },
    {
      "title": "pakistanlıların elinden telefonu almak",
      "entry_id": "137184662",
      "author": "087",
      "date": "08.05.2022 15:24",
      "content": "açık hava alanlarına da x-ray cihazı konularak devam ettirilebilir. zira sapıklığın büyük bölümü parklarda ve bahçelerde gerçekleşiyor.",
      "has_external_url": false
    },
    {
      "title": "pakistanlıların elinden telefonu almak",
      "entry_id": "137184765",
      "author": "ufo goren masum cityli",
      "date": "08.05.2022 15:28",
      "content": "lan adamlar mezar kazıp 2 gün önce ölmüş 2 yaşındaki kıza tecavüz ediyor, hemide 14 kişi. buda kalkmış telefonlarını alalım diyor. yakında istersen çelikten koruyucu tak g.tune onu bile deler bu tecavüzcü o.cocuklari.\n\nsenin kafa soylu ve hulusi kafası, alt tarafı selfie çekiyorlar demekle aynı şey.",
      "has_external_url": false
    },
    {
      "title": "pakistanlıların elinden telefonu almak",
      "entry_id": "137184831",
      "author": "737aviator",
      "date": "08.05.2022 15:30",
      "content": "arkadaşlar çözüm bu değil. çözümü açıklıyorum; aliexpress'ten 12.99 dolara çelik don alıp geziyoruz.",
      "has_external_url": false
    },
    {
      "title": "pakistanlıların elinden telefonu almak",
      "entry_id": "137185061",
      "author": "hergelemimar",
      "date": "08.05.2022 15:37",
      "content": "tek çözüm yönetimin değişmesi. onun dışında ne yapsanız boş",
      "has_external_url": false
    },
    {
      "title": "pakistanlıların elinden telefonu almak",
      "entry_id": "137185071",
      "author": "kutsal cesi",
      "date": "08.05.2022 15:37",
      "content": "xr cihazını sınırlara koyalım ki telefonu dötlerine sokmuş olabilirler diyerek artırdığım sorunsal.\n\n(bkz: ama kafamız nasıl güzel.)",
      "has_external_url": false
    },
    {
      "title": "pakistanlıların elinden telefonu almak",
      "entry_id": "137185290",
      "author": "zeksek",
      "date": "08.05.2022 15:44",
      "content": "bu yaptığın sadece kanıtları yok eder sapıklıkları devam eder.",
      "has_external_url": false
    },
    {
      "title": "pakistanlıların elinden telefonu almak",
      "entry_id": "137186164",
      "author": "flatearth",
      "date": "08.05.2022 16:12",
      "content": "ellerinden almak yetmez",
      "has_external_url": false
    },
    {
      "title": "pakistanlıların elinden telefonu almak",
      "entry_id": "137186256",
      "author": "labelladifference",
      "date": "08.05.2022 16:15",
      "content": "bence yakaladığımız yerde hadım edelim. daha mantıklı olduğunu itiraf edin.",
      "has_external_url": false
    },
    {
      "title": "pakistanlıların elinden telefonu almak",
      "entry_id": "137186549",
      "author": "amondeal",
      "date": "08.05.2022 16:24",
      "content": "ve götüne sokmak diye devam etmesi gereken başlık.",
      "has_external_url": false
    },
    {
      "title": "pakistanlıların elinden telefonu almak",
      "entry_id": "137187891",
      "author": "davidbowie",
      "date": "08.05.2022 17:04",
      "content": "sınırda verilecek spironolactone, dutasteride, finasteride ve benzeri anti androjenler ile hepsini muma çevirir, rahip okuluna kaydettiririz",
      "has_external_url": false
    },
    {
      "title": "pakistanlıların elinden telefonu almak",
      "entry_id": "137188415",
      "author": "yunusemrea",
      "date": "08.05.2022 17:21",
      "content": "yetmez, telefonu götlerine sokup akabinde hadım edilmelidirler",
      "has_external_url": false
    }
  ]
}